[
  {
    "deleted" : false,
    "startDate" : "2021-07-03T05:10:16Z",
    "body" : "It was Katherine’s 18th Birthday on Friday. Due to the COVID Lockdown continuing in Brisbane, there was no actual birthday celebration. Katherine baked a 🎂",
    "lastSaved" : "2025-12-21T03:18:52Z",
    "endDate" : "2021-07-03T05:10:16Z",
    "id" : "FE53BEA1-EDCB-4897-A15A-865B24030AC8",
    "source" : "LocoKit",
    "creationDate" : "2025-12-21T03:18:52Z"
  },
  {
    "deleted" : false,
    "startDate" : "2021-07-03T07:31:50Z",
    "body" : "Went to Coles at Mt Gravatt but Arc missed the trip there.",
    "lastSaved" : "2025-12-21T03:18:52Z",
    "endDate" : "2021-07-03T07:31:50Z",
    "id" : "B925304B-E373-451F-8CA9-B301F08C6EA4",
    "source" : "LocoKit",
    "creationDate" : "2025-12-21T03:18:52Z"
  },
  {
    "deleted" : false,
    "startDate" : "2021-07-03T07:31:50Z",
    "body" : "There were three people at Coles not wearing masks",
    "lastSaved" : "2025-12-21T03:18:52Z",
    "endDate" : "2021-07-03T07:31:50Z",
    "id" : "3CAA9EB2-9504-4639-A669-754F3DE5DF31",
    "source" : "LocoKit",
    "creationDate" : "2025-12-21T03:18:52Z"
  },
  {
    "deleted" : false,
    "startDate" : "2021-07-03T08:52:44Z",
    "body" : "Katherine made birthday cake for her best friends and I drove to their homes to help her deliver it.",
    "lastSaved" : "2025-12-21T03:18:52Z",
    "endDate" : "2021-07-03T08:52:44Z",
    "id" : "2C8AF0BD-66E3-4142-9514-F232C1E427A8",
    "source" : "LocoKit",
    "creationDate" : "2025-12-21T03:18:52Z"
  },
  {
    "deleted" : false,
    "startDate" : "2021-07-03T09:32:28Z",
    "body" : "I plugged the LEAF in for an hour to prepare for the next trip. I wasn’t sure how far we had to go.",
    "lastSaved" : "2025-12-21T03:18:52Z",
    "endDate" : "2021-07-03T09:32:28Z",
    "id" : "57EDC2A1-57E3-4ABB-9F6D-99343694D594",
    "source" : "LocoKit",
    "creationDate" : "2025-12-21T03:18:52Z"
  },
  {
    "deleted" : false,
    "startDate" : "2021-07-03T10:19:22Z",
    "body" : "The second cake delivery trips",
    "lastSaved" : "2025-12-21T03:18:52Z",
    "endDate" : "2021-07-03T10:19:22Z",
    "id" : "2C27D957-0407-474C-A729-EC0ED2D795D8",
    "source" : "LocoKit",
    "creationDate" : "2025-12-21T03:18:52Z"
  },
  {
    "deleted" : false,
    "startDate" : "2021-07-04T03:12:22Z",
    "body" : "Stopped to pump up the tyres and fill up the petrol tank in the WRX. BPs iphone app works the opposite way to the Caltex version. You have to unlock the pump first using the app, then fill the tank. So I ended up going into the service station to pay. Anita reminded me to check in using the app.",
    "lastSaved" : "2025-12-21T03:18:52Z",
    "endDate" : "2021-07-04T03:12:22Z",
    "id" : "9268F742-38E3-4983-97AC-99BA2AD35750",
    "source" : "LocoKit",
    "creationDate" : "2025-12-21T03:18:52Z"
  },
  {
    "deleted" : false,
    "startDate" : "2021-07-04T03:12:22Z",
    "body" : "We decided to take the WRX because we are still waiting for a replacement windscreen washer bottle and headlights for the Forester.",
    "lastSaved" : "2025-12-21T03:18:52Z",
    "endDate" : "2021-07-04T03:12:22Z",
    "id" : "F7AB5246-98CC-44AD-ADB0-6BB1B239DF66",
    "source" : "LocoKit",
    "creationDate" : "2025-12-21T03:18:52Z"
  },
  {
    "deleted" : false,
    "startDate" : "2021-07-04T04:17:19Z",
    "body" : "We stopped at Aratula to buy some local fruit for our stay. Most people were wearing masks.",
    "lastSaved" : "2025-12-21T03:18:52Z",
    "endDate" : "2021-07-04T04:17:19Z",
    "id" : "922AE6AE-3639-4927-805B-7FE3B8C86908",
    "source" : "LocoKit",
    "creationDate" : "2025-12-21T03:18:52Z"
  },
  {
    "deleted" : false,
    "startDate" : "2021-07-04T05:18:17Z",
    "body" : "We stopped for a break at a park beside the River in Warwick. The River was overflowing a little but nowhere near as much as the larger floods! There was a big sign there showing the previous flood levels. \n\nThere was a man riding his horse along the path beside the River.",
    "lastSaved" : "2025-12-21T03:18:52Z",
    "endDate" : "2021-07-04T05:18:17Z",
    "id" : "72D01A1E-D360-4B82-A7C0-DE064024B81A",
    "source" : "LocoKit",
    "creationDate" : "2025-12-21T03:18:52Z"
  },
  {
    "deleted" : false,
    "startDate" : "2021-07-04T06:18:00Z",
    "body" : "We stopped at the Liberty Petrol station to buy some drinks. The COVID app didn’t work as expected due to a lack of internet access, but entering the location code worked.",
    "lastSaved" : "2025-12-21T03:18:52Z",
    "endDate" : "2021-07-04T06:18:00Z",
    "id" : "A298422B-A832-4804-A22F-F9EB56150C45",
    "source" : "LocoKit",
    "creationDate" : "2025-12-21T03:18:52Z"
  },
  {
    "deleted" : false,
    "startDate" : "2021-07-04T06:49:58Z",
    "body" : "Arrived at the reception for the lodge. The European owner tested our temperature and disinfected our hands and the soles of our shoes!",
    "lastSaved" : "2025-12-21T03:18:52Z",
    "endDate" : "2021-07-04T06:49:58Z",
    "id" : "0CFEB562-8570-41C6-8709-ECF3040F656B",
    "source" : "LocoKit",
    "creationDate" : "2025-12-21T03:18:52Z"
  },
  {
    "deleted" : false,
    "startDate" : "2021-07-04T07:10:04Z",
    "body" : "We are in Chalet 13. We think this is the same chalet we stayed in with Anita dad. I only remember the bar rock area outside the chalet. This would be our third stay here.",
    "lastSaved" : "2025-12-21T03:18:52Z",
    "endDate" : "2021-07-04T07:10:04Z",
    "id" : "9203AB2C-D110-4D8A-BB9B-DD248645D29D",
    "source" : "LocoKit",
    "creationDate" : "2025-12-21T03:18:52Z"
  },
  {
    "deleted" : false,
    "startDate" : "2021-07-04T07:23:31Z",
    "body" : "I walked down to the reception because the phone doesn’t work. It’s not far anyway. There was a lot of ash in the fireplace so I wanted help removing it.\n\nOne of the staff came up afterwards to start the fire and explained what the thing on the handle of the Webber was.",
    "lastSaved" : "2025-12-21T03:18:52Z",
    "endDate" : "2021-07-04T07:23:31Z",
    "id" : "4E622B0F-3131-45FB-A0F8-174B68381964",
    "source" : "LocoKit",
    "creationDate" : "2025-12-21T03:18:52Z"
  },
  {
    "deleted" : false,
    "startDate" : "2021-07-04T22:53:46Z",
    "body" : "Anita says it was slightly below zero when she got up this morning.",
    "lastSaved" : "2025-12-21T03:18:52Z",
    "endDate" : "2021-07-04T22:53:46Z",
    "id" : "077B3E13-BEEF-4414-A6DE-7B71C7906EB0",
    "source" : "LocoKit",
    "creationDate" : "2025-12-21T03:18:52Z"
  },
  {
    "deleted" : false,
    "startDate" : "2021-07-05T01:50:15Z",
    "body" : "Walked back to the Chalet to retrieve the EF-EFS adaptor for the camera.",
    "lastSaved" : "2025-12-21T03:18:52Z",
    "endDate" : "2021-07-05T01:50:15Z",
    "id" : "27A9D388-C47C-4DA1-BF4B-921AD92722F5",
    "source" : "LocoKit",
    "creationDate" : "2025-12-21T03:18:52Z"
  },
  {
    "deleted" : false,
    "startDate" : "2021-07-05T03:57:40Z",
    "body" : "There’s been a lot of regrowth after good rains and the bushfire about two years ago.",
    "lastSaved" : "2025-12-21T03:18:52Z",
    "endDate" : "2021-07-05T03:57:40Z",
    "id" : "F16C4B73-F30A-4119-AAF1-6B677323CADC",
    "source" : "LocoKit",
    "creationDate" : "2025-12-21T03:18:52Z"
  },
  {
    "deleted" : false,
    "startDate" : "2021-07-05T04:11:19Z",
    "body" : "Probably more water than in the last few years of dry conditions. I will have to look at old photos to compare.",
    "lastSaved" : "2025-12-21T03:18:52Z",
    "endDate" : "2021-07-05T04:11:19Z",
    "id" : "4B246A4C-F788-4CBF-99DE-8E85BDACC31A",
    "source" : "LocoKit",
    "creationDate" : "2025-12-21T03:18:52Z"
  },
  {
    "deleted" : false,
    "startDate" : "2021-07-05T11:33:40Z",
    "body" : "I dropped in at the reception building and spoke to the caretaker about our fireplace. He came up to the Chalet afterwards and emptied the ash. He also refilled it with firewood ready for the evening.",
    "lastSaved" : "2025-12-21T03:18:52Z",
    "endDate" : "2021-07-05T11:33:40Z",
    "id" : "36970DB7-58C3-4F9F-9204-E8903C8E3743",
    "source" : "LocoKit",
    "creationDate" : "2025-12-21T03:18:52Z"
  },
  {
    "deleted" : false,
    "startDate" : "2021-07-06T00:08:06Z",
    "body" : "We watched “WW87” last night on the iPad. I rented and downloaded the movie before we left Brisbane.\n\nAfter Anita went to be Katherine and I watched an episode of “WandaVision”.",
    "lastSaved" : "2025-12-21T03:18:52Z",
    "endDate" : "2021-07-06T00:08:06Z",
    "id" : "087570E5-290B-4478-B71E-EB8C3284FC65",
    "source" : "LocoKit",
    "creationDate" : "2025-12-21T03:18:52Z"
  },
  {
    "deleted" : false,
    "startDate" : "2021-07-06T00:08:06Z",
    "body" : "At best we are getting 1 bar of 4G signal around the whole area. It’s even the same at the top of the hills. I’ve gone back to using my text-only newsreader.",
    "lastSaved" : "2025-12-21T03:18:52Z",
    "endDate" : "2021-07-06T00:08:06Z",
    "id" : "9410F08E-621D-4D48-AFB4-0579F45C0E17",
    "source" : "LocoKit",
    "creationDate" : "2025-12-21T03:18:52Z"
  },
  {
    "deleted" : false,
    "startDate" : "2021-07-06T01:29:56Z",
    "body" : "I took some garbage down to the laundry where they keep the bins. I didn’t see any laundry machines there, but there were two Tesla destination chargers on the end wall.",
    "lastSaved" : "2025-12-21T03:18:52Z",
    "endDate" : "2021-07-06T01:29:56Z",
    "id" : "8FBE0881-5695-4C29-BBB0-50F76B0BECAE",
    "source" : "LocoKit",
    "creationDate" : "2025-12-21T03:18:52Z"
  },
  {
    "deleted" : false,
    "startDate" : "2021-07-06T02:26:52Z",
    "body" : "This is supposed to be the easy walking day. First it was Whale Rock. I suppose it does look a bit like a whale but I wouldn’t make a special trip to see it.",
    "lastSaved" : "2025-12-21T03:18:52Z",
    "endDate" : "2021-07-06T02:26:52Z",
    "id" : "369D5F64-3BC3-4B4F-9A59-8B174BA19897",
    "source" : "LocoKit",
    "creationDate" : "2025-12-21T03:18:52Z"
  },
  {
    "deleted" : false,
    "startDate" : "2021-07-06T02:55:52Z",
    "body" : "We walked back and followed the Bird Walk which came out at Ramsay’s Rest near a big dam. There were half a dozen kangaroos grazing there.",
    "lastSaved" : "2025-12-21T03:18:52Z",
    "endDate" : "2021-07-06T02:55:52Z",
    "id" : "D70241E0-DC6C-44C6-B7BF-46C098744317",
    "source" : "LocoKit",
    "creationDate" : "2025-12-21T03:18:52Z"
  },
  {
    "deleted" : false,
    "startDate" : "2021-07-06T03:08:04Z",
    "body" : "I stopped to record the sound of the frogs in the dam.",
    "lastSaved" : "2025-12-21T03:18:52Z",
    "endDate" : "2021-07-06T03:08:04Z",
    "id" : "170ED51D-BDDC-4EAB-9C23-B280CA6DBED3",
    "source" : "LocoKit",
    "creationDate" : "2025-12-21T03:18:52Z"
  },
  {
    "deleted" : false,
    "startDate" : "2021-07-06T04:10:22Z",
    "body" : "This was the hardest part of today’s walk as it involved going uphill to about 980metres. My legs were starting to give out after two days of walking around the area.",
    "lastSaved" : "2025-12-21T03:18:52Z",
    "endDate" : "2021-07-06T04:10:22Z",
    "id" : "302D5CDD-7FEF-4AB9-A322-8D25D833DDEB",
    "source" : "LocoKit",
    "creationDate" : "2025-12-21T03:18:52Z"
  },
  {
    "deleted" : false,
    "startDate" : "2021-07-06T04:41:48Z",
    "body" : "We stopped at Cathedral Arch and had something to eat. Some people came up after we had finished, so we decided to head back down to the lodge. They were the first people we’d seen on the tracks for the whole stay!",
    "lastSaved" : "2025-12-21T03:18:52Z",
    "endDate" : "2021-07-06T04:41:48Z",
    "id" : "83472C49-571B-4DFF-BD7C-34861AE075DF",
    "source" : "LocoKit",
    "creationDate" : "2025-12-21T03:18:52Z"
  },
  {
    "deleted" : false,
    "startDate" : "2021-07-06T05:27:29Z",
    "body" : "I went down to the lodge to use the wifi connection. I downloaded some YouTube videos for later.",
    "lastSaved" : "2025-12-21T03:18:52Z",
    "endDate" : "2021-07-06T05:27:29Z",
    "id" : "A14B9E67-2AF2-4B19-8D88-F34DF99C22E5",
    "source" : "LocoKit",
    "creationDate" : "2025-12-21T03:18:52Z"
  },
  {
    "deleted" : false,
    "startDate" : "2021-07-06T09:33:15Z",
    "body" : "Back at the Chalet I started the fire and the Webber BBQ. It literally takes hours to cook the dinner.\n\nA bird flew up onto the railing. It could smell the food. Anita came out to guard the steak and rissoles from the bird. He eventually flew off as the sun set on our last evening at the chalet.\n\nWe watched the movie “Luca” on the iPad. The fire was burning really well tonight and we still had extra firewood.",
    "lastSaved" : "2025-12-21T03:18:52Z",
    "endDate" : "2021-07-06T09:33:15Z",
    "id" : "6AC8BBE9-1AFE-4615-BC66-0041B48E95F4",
    "source" : "LocoKit",
    "creationDate" : "2025-12-21T03:18:52Z"
  },
  {
    "deleted" : false,
    "startDate" : "2021-07-06T22:00:02Z",
    "body" : "Had to get up early this morning. We have to be out by 10am. The plan is to check out and then go to the National park just down the same road and do some of the walks there before heading home to Brisbane.",
    "lastSaved" : "2025-12-21T03:18:52Z",
    "endDate" : "2021-07-06T22:00:02Z",
    "id" : "802CC929-0E11-484A-AAB4-A3D9AFC4783F",
    "source" : "LocoKit",
    "creationDate" : "2025-12-21T03:18:52Z"
  },
  {
    "deleted" : false,
    "startDate" : "2021-07-06T22:02:28Z",
    "body" : "Things I didn’t use - \n\n* The D7 Canon camera\n* The tripods\n* The DJI stabiliser\n* The Ski jacket\n* The Headphones\n* The EarPods Pro.",
    "lastSaved" : "2025-12-21T03:18:52Z",
    "endDate" : "2021-07-06T22:02:28Z",
    "id" : "53F5F5D2-0D26-4D8F-8584-FC147F7BA476",
    "source" : "LocoKit",
    "creationDate" : "2025-12-21T03:18:52Z"
  },
  {
    "deleted" : false,
    "startDate" : "2021-07-06T23:42:08Z",
    "body" : "Took the garbage down to the laundry.",
    "lastSaved" : "2025-12-21T03:18:52Z",
    "endDate" : "2021-07-06T23:42:08Z",
    "id" : "456B02AA-FFB5-42A4-855D-67B5A2924D1B",
    "source" : "LocoKit",
    "creationDate" : "2025-12-21T03:18:52Z"
  },
  {
    "deleted" : false,
    "startDate" : "2021-07-07T00:07:49Z",
    "body" : "We drove down to the National Park. It was almost full!",
    "lastSaved" : "2025-12-21T03:18:52Z",
    "endDate" : "2021-07-07T00:07:49Z",
    "id" : "FF8DA555-6422-42DC-84AE-18058128ABB5",
    "source" : "LocoKit",
    "creationDate" : "2025-12-21T03:18:52Z"
  },
  {
    "deleted" : false,
    "startDate" : "2021-07-07T00:15:46Z",
    "body" : "I walked onto a flat rock to the side of the track to take some photos",
    "lastSaved" : "2025-12-21T03:18:52Z",
    "endDate" : "2021-07-07T00:15:46Z",
    "id" : "6546FE40-D4FE-40B7-B415-1F27AD6ED435",
    "source" : "LocoKit",
    "creationDate" : "2025-12-21T03:18:52Z"
  },
  {
    "deleted" : false,
    "startDate" : "2021-07-07T00:21:00Z",
    "body" : "I took what turned out to be a huge shortcut when I walked over to get a closer look at some interesting rock formations.",
    "lastSaved" : "2025-12-21T03:18:52Z",
    "endDate" : "2021-07-07T00:21:00Z",
    "id" : "2973A2EA-79AF-4CA1-B793-01DA447C5538",
    "source" : "LocoKit",
    "creationDate" : "2025-12-21T03:18:52Z"
  },
  {
    "deleted" : false,
    "startDate" : "2021-07-07T00:26:42Z",
    "body" : "There were some people at the arch taking forever to take photos. Everyone is an instagramer these days!",
    "lastSaved" : "2025-12-21T03:18:52Z",
    "endDate" : "2021-07-07T00:26:42Z",
    "id" : "EED06252-BC17-45B7-A054-6F6A4401A14A",
    "source" : "LocoKit",
    "creationDate" : "2025-12-21T03:18:52Z"
  },
  {
    "deleted" : false,
    "startDate" : "2021-07-07T00:43:44Z",
    "body" : "It was a fairly tough walk with a 100 metre climb. There were lots of people on the trail. Many did not look very fit to be doing the walk!",
    "lastSaved" : "2025-12-21T03:18:52Z",
    "endDate" : "2021-07-07T00:43:44Z",
    "id" : "A8F364B8-4836-400A-B2AD-A98606B63FD0",
    "source" : "LocoKit",
    "creationDate" : "2025-12-21T03:18:52Z"
  },
  {
    "deleted" : false,
    "startDate" : "2021-07-07T01:02:47Z",
    "body" : "We weren’t intending to go up to the top of the Pyramids, but it didn’t look as bad as I remembered and the weather was perfect. Unfortunately Katherine was wearing her sand-shoes and they had no grip. She said she wouldn’t have gone up anyway.",
    "lastSaved" : "2025-12-21T03:18:52Z",
    "endDate" : "2021-07-07T01:02:47Z",
    "id" : "47D73DDB-EA20-46BC-8F04-CF207ECBEADE",
    "source" : "LocoKit",
    "creationDate" : "2025-12-21T03:18:52Z"
  },
  {
    "deleted" : false,
    "startDate" : "2021-07-07T01:02:47Z",
    "body" : "As a bonus there was around 3 a 4 bars of 4G signal near the top. My Apple Watch went off frequently as all the notifications caught up with me.",
    "lastSaved" : "2025-12-21T03:18:52Z",
    "endDate" : "2021-07-07T01:02:47Z",
    "id" : "47106F9E-C208-4ABD-BFCE-FFEEF8BBFC4C",
    "source" : "LocoKit",
    "creationDate" : "2025-12-21T03:18:52Z"
  },
  {
    "deleted" : false,
    "startDate" : "2021-07-07T01:27:59Z",
    "body" : "A consolation prize version of a balancing rock. There is a much bigger one at the top of the Pyramids.",
    "lastSaved" : "2025-12-21T03:18:52Z",
    "endDate" : "2021-07-07T01:27:59Z",
    "id" : "5218BEB5-B1C3-4AAE-90C2-2EA5E5555D01",
    "source" : "LocoKit",
    "creationDate" : "2025-12-21T03:18:52Z"
  },
  {
    "deleted" : false,
    "startDate" : "2021-07-07T02:44:38Z",
    "body" : "I refilled the WRX. It was down to half a tank from the drive to Girraween. There were Roadworks right out front of the gas station and McDonalds which complicates the process.\n\nThere was a camel in a pen there.",
    "lastSaved" : "2025-12-21T03:18:52Z",
    "endDate" : "2021-07-07T02:44:38Z",
    "id" : "389F1E99-888A-47EF-A122-542B350CDA61",
    "source" : "LocoKit",
    "creationDate" : "2025-12-21T03:18:52Z"
  },
  {
    "deleted" : false,
    "startDate" : "2021-07-07T04:25:03Z",
    "body" : "We decided to have a late lunch at Warwick because it’s a much larger town than Stanthorpe. We bought some takeaway from KFC and coffee from McDonalds and took it to a park to eat it at a park table.",
    "lastSaved" : "2025-12-21T03:18:52Z",
    "endDate" : "2021-07-07T04:25:03Z",
    "id" : "C58E96C3-75C6-4E95-A693-7D372BC49179",
    "source" : "LocoKit",
    "creationDate" : "2025-12-21T03:18:52Z"
  },
  {
    "deleted" : false,
    "startDate" : "2021-07-07T04:47:49Z",
    "body" : "Toilet break",
    "lastSaved" : "2025-12-21T03:18:52Z",
    "endDate" : "2021-07-07T04:47:49Z",
    "id" : "B58EDC7E-991D-41E9-BFA0-C51AF273580A",
    "source" : "LocoKit",
    "creationDate" : "2025-12-21T03:18:52Z"
  },
  {
    "deleted" : false,
    "startDate" : "2021-07-08T02:49:26Z",
    "body" : "Katherine had a dentists appointment. I’m waiting in the car but I will see if the cafeteria is open nearby?",
    "lastSaved" : "2025-12-21T03:18:52Z",
    "endDate" : "2021-07-08T02:49:26Z",
    "id" : "00A9BDAB-319F-48A8-B05C-02B71D60AC66",
    "source" : "LocoKit",
    "creationDate" : "2025-12-21T03:18:52Z"
  },
  {
    "deleted" : false,
    "startDate" : "2021-07-08T02:54:53Z",
    "body" : "Ordered coffee to takeaway at the Technology Office Park Cafe. The cafe is busy. Everyone is wearing masks.",
    "lastSaved" : "2025-12-21T03:18:52Z",
    "endDate" : "2021-07-08T02:54:53Z",
    "id" : "93B3E927-EE62-49E9-A015-04683837AFA6",
    "source" : "LocoKit",
    "creationDate" : "2025-12-21T03:18:52Z"
  },
  {
    "deleted" : false,
    "startDate" : "2021-07-08T03:01:30Z",
    "body" : "Waiting in the air conditioned LEAF, drinking coffee and listening to YouTube. It’s raining now.",
    "lastSaved" : "2025-12-21T03:18:52Z",
    "endDate" : "2021-07-08T03:01:30Z",
    "id" : "F72E0F46-0ECE-42FE-8F43-D1B31F60AC97",
    "source" : "LocoKit",
    "creationDate" : "2025-12-21T03:18:52Z"
  },
  {
    "deleted" : false,
    "startDate" : "2021-07-08T03:23:19Z",
    "body" : "Katherine bought some modelling clay to make some key rings.",
    "lastSaved" : "2025-12-21T03:18:52Z",
    "endDate" : "2021-07-08T03:23:19Z",
    "id" : "2813FF8E-E6C0-4354-B657-64CFF825D4E8",
    "source" : "LocoKit",
    "creationDate" : "2025-12-21T03:18:52Z"
  },
  {
    "deleted" : false,
    "startDate" : "2021-07-08T03:42:52Z",
    "body" : "Anita is picking up her IV medication ready for next Tuesday’s appointment",
    "lastSaved" : "2025-12-21T03:18:52Z",
    "endDate" : "2021-07-08T03:42:52Z",
    "id" : "7BA07F45-B5B3-4A0A-920A-E7C97CBE11F7",
    "source" : "LocoKit",
    "creationDate" : "2025-12-21T03:18:52Z"
  },
  {
    "deleted" : false,
    "startDate" : "2021-07-08T04:06:20Z",
    "body" : "Katherine is buying more material from Spotlight.",
    "lastSaved" : "2025-12-21T03:18:52Z",
    "endDate" : "2021-07-08T04:06:20Z",
    "id" : "2EB3AE93-573A-45C2-BC6A-706FE1D953E6",
    "source" : "LocoKit",
    "creationDate" : "2025-12-21T03:18:52Z"
  },
  {
    "deleted" : false,
    "startDate" : "2021-07-08T07:17:50Z",
    "body" : "Took Anita to her appointment at Queensland Xray. I dropped her off at the main entrance and then parked below the hospital to wait.",
    "lastSaved" : "2025-12-21T03:18:52Z",
    "endDate" : "2021-07-08T07:17:50Z",
    "id" : "657F272C-F982-4966-984B-9B8F4B67E44C",
    "source" : "LocoKit",
    "creationDate" : "2025-12-21T03:18:52Z"
  },
  {
    "deleted" : false,
    "startDate" : "2021-07-08T07:40:42Z",
    "body" : "We ran out of disposable masks so I stopped at Bunnings to get some more, but they were out. So was the Chemist Warehouse!\n\nI found some at the other chemist for $34.00 for a carton of 50 masks.",
    "lastSaved" : "2025-12-21T03:18:52Z",
    "endDate" : "2021-07-08T07:40:42Z",
    "id" : "AE32DFBC-ADBC-47ED-B19E-DF9EA6212E3A",
    "source" : "LocoKit",
    "creationDate" : "2025-12-21T03:18:52Z"
  },
  {
    "deleted" : false,
    "startDate" : "2021-07-08T07:45:47Z",
    "body" : "Sold out here as well",
    "lastSaved" : "2025-12-21T03:18:52Z",
    "endDate" : "2021-07-08T07:45:47Z",
    "id" : "DB088A69-7627-4CA3-AB41-B1B7CFC7958F",
    "source" : "LocoKit",
    "creationDate" : "2025-12-21T03:18:52Z"
  },
  {
    "deleted" : false,
    "startDate" : "2021-07-09T02:23:03Z",
    "body" : "Lunch - pumpkin soup and coffee. I noticed while sitting in the restaurant that a few people were not wearing masks. Some used the excuse of drinking or eating while walking for not wearing it.",
    "lastSaved" : "2025-12-21T03:18:52Z",
    "endDate" : "2021-07-09T02:23:03Z",
    "id" : "11C1A4A7-E747-4EA3-AE62-942097258610",
    "source" : "LocoKit",
    "creationDate" : "2025-12-21T03:18:52Z"
  },
  {
    "deleted" : false,
    "startDate" : "2021-07-09T02:54:55Z",
    "body" : "Anita bought some 3Kg weights. The bicycle ergometers are around $800 these days.",
    "lastSaved" : "2025-12-21T03:18:52Z",
    "endDate" : "2021-07-09T02:54:55Z",
    "id" : "6339A043-2EDA-4A75-8F1C-07E484ED7EA9",
    "source" : "LocoKit",
    "creationDate" : "2025-12-21T03:18:52Z"
  },
  {
    "deleted" : false,
    "startDate" : "2021-07-09T03:05:09Z",
    "body" : "Just bought milk and bread",
    "lastSaved" : "2025-12-21T03:18:52Z",
    "endDate" : "2021-07-09T03:05:09Z",
    "id" : "40F1D075-B33B-4020-A401-D8AE321EF314",
    "source" : "LocoKit",
    "creationDate" : "2025-12-21T03:18:52Z"
  },
  {
    "deleted" : false,
    "startDate" : "2021-07-09T05:33:11Z",
    "body" : "We went to Coles to do the real shopping for groceries. There were two women not wearing masks and kept ending up in the same place as us; even when we went to the checkout.",
    "lastSaved" : "2025-12-21T03:18:52Z",
    "endDate" : "2021-07-09T05:33:11Z",
    "id" : "7D0EB8DD-0D29-49BC-B791-4866EDBC10F6",
    "source" : "LocoKit",
    "creationDate" : "2025-12-21T03:18:52Z"
  },
  {
    "deleted" : false,
    "startDate" : "2021-07-09T10:26:47Z",
    "body" : "Took a couple of wrong turns on the way so ended up using a toll road!",
    "lastSaved" : "2025-12-21T03:18:52Z",
    "endDate" : "2021-07-09T10:26:47Z",
    "id" : "1E381ABE-DEA4-4AF1-9760-93D5575FBE0C",
    "source" : "LocoKit",
    "creationDate" : "2025-12-21T03:18:52Z"
  },
  {
    "deleted" : false,
    "startDate" : "2021-07-09T11:06:47Z",
    "body" : "Checked out the Evie Network chargers at the DFO near the airport. It’s currently the biggest charging setup in Brisbane with 4 charging bays.\n\nThey charge 40c per kWh. That’s twice as much as the QESH chargers. Evie have obviously placed the chargers in a location that suits people heading to the coast on the highway. But they really should have some faster chargers than the 50kW units.",
    "lastSaved" : "2025-12-21T03:18:52Z",
    "endDate" : "2021-07-09T11:06:47Z",
    "id" : "C78FE632-7CC4-4759-BE89-505230399AF4",
    "source" : "LocoKit",
    "creationDate" : "2025-12-21T03:18:52Z"
  },
  {
    "deleted" : false,
    "startDate" : "2021-07-09T11:46:36Z",
    "body" : "Drove back through the city on the way home while I listened to a K-Pop radio station.",
    "lastSaved" : "2025-12-21T03:18:52Z",
    "endDate" : "2021-07-09T11:46:36Z",
    "id" : "58F7785D-7EAD-40C3-BA26-3EAD69D9822E",
    "source" : "LocoKit",
    "creationDate" : "2025-12-21T03:18:52Z"
  },
  {
    "deleted" : false,
    "startDate" : "2021-07-10T02:46:23Z",
    "body" : "Round trip to McDonalds",
    "lastSaved" : "2025-12-21T03:18:52Z",
    "endDate" : "2021-07-10T02:46:23Z",
    "id" : "EC5B68AB-8CDB-49D0-B96B-4B2FFE3EB6CC",
    "source" : "LocoKit",
    "creationDate" : "2025-12-21T03:18:52Z"
  },
  {
    "deleted" : false,
    "startDate" : "2021-07-10T06:26:56Z",
    "body" : "I left the LEAF out on the driveway to clean it. I also assembled the mechanics trolley. It’s also a seat.",
    "lastSaved" : "2025-12-21T03:18:52Z",
    "endDate" : "2021-07-10T06:26:56Z",
    "id" : "6E2A77E4-9032-4CF8-A516-E7B7C8EFD61C",
    "source" : "LocoKit",
    "creationDate" : "2025-12-21T03:18:52Z"
  },
  {
    "deleted" : false,
    "startDate" : "2021-07-10T10:07:35Z",
    "body" : "Dinner from Red Rooster. They have changed their menu so the names are different. Katherine ordered a Reds Burger box",
    "lastSaved" : "2025-12-21T03:18:52Z",
    "endDate" : "2021-07-10T10:07:35Z",
    "id" : "4074ED56-0EF0-4A58-B07A-4A6DB42901AD",
    "source" : "LocoKit",
    "creationDate" : "2025-12-21T03:18:52Z"
  },
  {
    "deleted" : false,
    "startDate" : "2021-07-12T21:56:53Z",
    "body" : "Anita came along for the ride to take Katherine to school. I bought breakfast at McDonalds",
    "lastSaved" : "2025-12-21T03:18:52Z",
    "endDate" : "2021-07-12T21:56:53Z",
    "id" : "016CA220-657B-4CFF-9B63-349622BDED6D",
    "source" : "LocoKit",
    "creationDate" : "2025-12-21T03:18:52Z"
  },
  {
    "deleted" : false,
    "startDate" : "2021-07-12T23:38:19Z",
    "body" : "Took Anita to the pathology centre for her special infusion. I waited in the LEAF.",
    "lastSaved" : "2025-12-21T03:18:52Z",
    "endDate" : "2021-07-12T23:38:19Z",
    "id" : "E8C951DE-85C6-429E-AEE1-5D69CECE48D9",
    "source" : "LocoKit",
    "creationDate" : "2025-12-21T03:18:52Z"
  },
  {
    "deleted" : false,
    "startDate" : "2021-07-13T02:38:21Z",
    "body" : "We had Red Rooster for lunch. They changed the menu, so the closest thing to a crispy chicken burger is the Red Burger?",
    "lastSaved" : "2025-12-21T03:18:52Z",
    "endDate" : "2021-07-13T02:38:21Z",
    "id" : "F954D773-4EFF-4660-9854-A5FDECA24CBC",
    "source" : "LocoKit",
    "creationDate" : "2025-12-21T03:18:52Z"
  },
  {
    "deleted" : false,
    "startDate" : "2021-07-13T22:29:22Z",
    "body" : "Major accident on the freeway caused problems on the secondary roads!",
    "lastSaved" : "2025-12-21T03:18:52Z",
    "endDate" : "2021-07-13T22:29:22Z",
    "id" : "F17C8081-65E3-4261-B53A-5BC55F91A244",
    "source" : "LocoKit",
    "creationDate" : "2025-12-21T03:18:52Z"
  },
  {
    "deleted" : false,
    "startDate" : "2021-07-14T06:54:03Z",
    "body" : "Waiting for Katherine. The side effects of Anita’s IV infusion have taken hold so I’m doing the pickup today",
    "lastSaved" : "2025-12-21T03:18:52Z",
    "endDate" : "2021-07-14T06:54:03Z",
    "id" : "B58C5046-0A9F-436C-B5E0-755DA7A8127E",
    "source" : "LocoKit",
    "creationDate" : "2025-12-21T03:18:52Z"
  },
  {
    "deleted" : false,
    "startDate" : "2021-07-14T06:54:42Z",
    "body" : "I forgot to check that Arc was running before I left work. It wasn’t running until I reached Redeemer when I opened it to check.",
    "lastSaved" : "2025-12-21T03:18:52Z",
    "endDate" : "2021-07-14T06:54:42Z",
    "id" : "727B89A1-49FC-4A49-8D60-AC831318F1D9",
    "source" : "LocoKit",
    "creationDate" : "2025-12-21T03:18:52Z"
  },
  {
    "deleted" : false,
    "startDate" : "2021-07-16T06:54:53Z",
    "body" : "Came home early to help Anita take Katherine to QYO rehearsals",
    "lastSaved" : "2025-12-21T03:18:52Z",
    "endDate" : "2021-07-16T06:54:53Z",
    "id" : "404455A3-A693-4F8A-949E-04587338CA2D",
    "source" : "LocoKit",
    "creationDate" : "2025-12-21T03:18:52Z"
  },
  {
    "deleted" : false,
    "startDate" : "2021-07-16T08:07:17Z",
    "body" : "We stopped at McDonals at Mt Gravatt to buy a salad.",
    "lastSaved" : "2025-12-21T03:18:52Z",
    "endDate" : "2021-07-16T08:07:17Z",
    "id" : "57F473F2-C065-4A13-9967-C0AD4046D4E3",
    "source" : "LocoKit",
    "creationDate" : "2025-12-21T03:18:52Z"
  },
  {
    "deleted" : false,
    "startDate" : "2021-07-16T11:10:59Z",
    "body" : "Katherine suddenly wanted to have chips.",
    "lastSaved" : "2025-12-21T03:18:52Z",
    "endDate" : "2021-07-16T11:10:59Z",
    "id" : "F2A302A6-24A0-4D62-A57A-150A95056896",
    "source" : "LocoKit",
    "creationDate" : "2025-12-21T03:18:52Z"
  },
  {
    "deleted" : false,
    "startDate" : "2021-07-17T05:10:02Z",
    "body" : "Anita needed some things for the budgie.",
    "lastSaved" : "2025-12-21T03:18:52Z",
    "endDate" : "2021-07-17T05:10:02Z",
    "id" : "67BDA789-D89D-406C-A1A1-6C233DA6B415",
    "source" : "LocoKit",
    "creationDate" : "2025-12-21T03:18:52Z"
  },
  {
    "deleted" : false,
    "startDate" : "2021-07-17T05:20:32Z",
    "body" : "I didn’t have lunch today so bought some chicken nuggets",
    "lastSaved" : "2025-12-21T03:18:52Z",
    "endDate" : "2021-07-17T05:20:32Z",
    "id" : "3E7AD03E-0D45-4112-AD33-E2C215D9C4FE",
    "source" : "LocoKit",
    "creationDate" : "2025-12-21T03:18:52Z"
  },
  {
    "deleted" : false,
    "startDate" : "2021-07-17T08:04:23Z",
    "body" : "Katherine wanted kebabs tonight.",
    "lastSaved" : "2025-12-21T03:18:52Z",
    "endDate" : "2021-07-17T08:04:23Z",
    "id" : "31979D36-8F8A-4354-827A-C473F661CC10",
    "source" : "LocoKit",
    "creationDate" : "2025-12-21T03:18:52Z"
  },
  {
    "deleted" : false,
    "startDate" : "2021-07-17T09:55:26Z",
    "body" : "Started watching a new series on Apple TV+ called “Schmigadoon”.",
    "lastSaved" : "2025-12-21T03:18:52Z",
    "endDate" : "2021-07-17T09:55:26Z",
    "id" : "70085412-FF91-49C9-820D-B81CDBEBD92E",
    "source" : "LocoKit",
    "creationDate" : "2025-12-21T03:18:52Z"
  },
  {
    "deleted" : false,
    "startDate" : "2021-07-19T11:31:21Z",
    "body" : "Picked up the Snoppa II steady-cam for the iPhone.",
    "lastSaved" : "2025-12-21T03:18:52Z",
    "endDate" : "2021-07-19T11:31:21Z",
    "id" : "83B3ED29-C747-4911-9140-A96C4E05F6B4",
    "source" : "LocoKit",
    "creationDate" : "2025-12-21T03:18:52Z"
  },
  {
    "deleted" : false,
    "startDate" : "2021-07-20T22:21:46Z",
    "body" : "Ate breakfast while parked at McDonalds to wait out the traffic.",
    "lastSaved" : "2025-12-21T03:18:52Z",
    "endDate" : "2021-07-20T22:21:46Z",
    "id" : "208066A6-7DDC-4073-9C68-A05382F8CC4E",
    "source" : "LocoKit",
    "creationDate" : "2025-12-21T03:18:52Z"
  },
  {
    "deleted" : false,
    "startDate" : "2021-07-21T03:06:47Z",
    "body" : "Dropped off the Zero 9 scooter to have the rear tyre replaced, and purchased to long range version of the VSETT 9+ at the same time.",
    "lastSaved" : "2025-12-21T03:18:52Z",
    "endDate" : "2021-07-21T03:06:47Z",
    "id" : "2A8F83A5-6E89-453E-84BD-BA2A008B0BDA",
    "source" : "LocoKit",
    "creationDate" : "2025-12-21T03:18:52Z"
  },
  {
    "deleted" : false,
    "startDate" : "2021-07-21T04:37:01Z",
    "body" : "First appointment. Probably more to come?",
    "lastSaved" : "2025-12-21T03:18:52Z",
    "endDate" : "2021-07-21T04:37:01Z",
    "id" : "0567494E-008E-40F9-9F97-336F74431B72",
    "source" : "LocoKit",
    "creationDate" : "2025-12-21T03:18:52Z"
  },
  {
    "deleted" : false,
    "startDate" : "2021-07-21T22:16:29Z",
    "body" : "Had the sausage and egg McMuffin for a change.",
    "lastSaved" : "2025-12-21T03:18:52Z",
    "endDate" : "2021-07-21T22:16:29Z",
    "id" : "C358ADB0-BE98-44A9-A5FD-5388D1BCC4C9",
    "source" : "LocoKit",
    "creationDate" : "2025-12-21T03:18:52Z"
  },
  {
    "deleted" : false,
    "startDate" : "2021-07-22T01:34:56Z",
    "body" : "Restocked the pills. I asked if they could dispense the single tablet that I needed for the biopsy in a few weeks time. They said they would, so I went back home to get the script.",
    "lastSaved" : "2025-12-21T03:18:52Z",
    "endDate" : "2021-07-22T01:34:56Z",
    "id" : "249B0DCC-41D0-45C4-A3FA-E5740881F154",
    "source" : "LocoKit",
    "creationDate" : "2025-12-21T03:18:52Z"
  },
  {
    "deleted" : false,
    "startDate" : "2021-07-22T02:07:17Z",
    "body" : "Drove to Bunnings first to buy 16 2032 batteries for the Actiwatches. The were $10 for an eight-battery pack.",
    "lastSaved" : "2025-12-21T03:18:52Z",
    "endDate" : "2021-07-22T02:07:17Z",
    "id" : "63DB3FA2-E437-463F-BC4E-25E52FC50753",
    "source" : "LocoKit",
    "creationDate" : "2025-12-21T03:18:52Z"
  },
  {
    "deleted" : false,
    "startDate" : "2021-07-22T02:17:52Z",
    "body" : "Back at the chemist for the single dose Ceprofloxacin.",
    "lastSaved" : "2025-12-21T03:18:52Z",
    "endDate" : "2021-07-22T02:17:52Z",
    "id" : "328CC0CA-F8B7-435B-9CAE-90A5790C63EB",
    "source" : "LocoKit",
    "creationDate" : "2025-12-21T03:18:52Z"
  },
  {
    "deleted" : false,
    "startDate" : "2021-07-22T03:16:02Z",
    "body" : "I decided to ride the new scooter to work. I added the lights to the handlebars and fitted the phone holder.",
    "lastSaved" : "2025-12-21T03:18:52Z",
    "endDate" : "2021-07-22T03:16:02Z",
    "id" : "2C1D735E-12A9-464D-A83A-62E3DFC68CCA",
    "source" : "LocoKit",
    "creationDate" : "2025-12-21T03:18:52Z"
  },
  {
    "deleted" : false,
    "startDate" : "2021-07-23T03:51:09Z",
    "body" : "It was the in-service day for the sleep unit.\n\nChloe dropped in with her baby boy Jai.",
    "lastSaved" : "2025-12-21T03:18:52Z",
    "endDate" : "2021-07-23T03:51:09Z",
    "id" : "8492F9A5-42BE-4B4C-93A8-B980D7D487FC",
    "source" : "LocoKit",
    "creationDate" : "2025-12-21T03:18:52Z"
  },
  {
    "deleted" : false,
    "startDate" : "2021-07-23T08:21:25Z",
    "body" : "Red Roast",
    "lastSaved" : "2025-12-21T03:18:52Z",
    "endDate" : "2021-07-23T08:21:25Z",
    "id" : "CBFD6654-C3BD-48E6-93EF-D158C218741E",
    "source" : "LocoKit",
    "creationDate" : "2025-12-21T03:18:52Z"
  },
  {
    "deleted" : false,
    "startDate" : "2021-07-23T10:18:55Z",
    "body" : "Waiting for Katherine. We got maybe the last parking spot inside the grounds of the museum. It would have been very difficult spot without the 360° camera view. It was raining too.",
    "lastSaved" : "2025-12-21T03:18:52Z",
    "endDate" : "2021-07-23T10:18:55Z",
    "id" : "6F9C14B0-2E97-43A4-BD83-3EA3E30533F8",
    "source" : "LocoKit",
    "creationDate" : "2025-12-21T03:18:52Z"
  },
  {
    "deleted" : false,
    "startDate" : "2021-07-24T00:46:01Z",
    "body" : "I rode the new scooter to Jake’s and we went in his car to Ride Electric to pick up the scooter.",
    "lastSaved" : "2025-12-21T03:18:52Z",
    "endDate" : "2021-07-24T00:46:01Z",
    "id" : "356396A9-675E-4BE4-803F-2B4C37F11759",
    "source" : "LocoKit",
    "creationDate" : "2025-12-21T03:18:52Z"
  },
  {
    "deleted" : false,
    "startDate" : "2021-07-24T01:18:44Z",
    "body" : "Picked up the scooter. Jake bought the twin lights that can be mounted on a helmet.",
    "lastSaved" : "2025-12-21T03:18:52Z",
    "endDate" : "2021-07-24T01:18:44Z",
    "id" : "A1CDE5CE-1C76-488C-B378-D760CD117E5F",
    "source" : "LocoKit",
    "creationDate" : "2025-12-21T03:18:52Z"
  },
  {
    "deleted" : false,
    "startDate" : "2021-07-24T02:58:29Z",
    "body" : "I stopped at the boardwalk to drink a poppa.",
    "lastSaved" : "2025-12-21T03:18:52Z",
    "endDate" : "2021-07-24T02:58:29Z",
    "id" : "B0F14C06-6EF8-431E-84E1-CB3CE1FCD3FC",
    "source" : "LocoKit",
    "creationDate" : "2025-12-21T03:18:52Z"
  },
  {
    "deleted" : false,
    "startDate" : "2021-07-24T08:36:40Z",
    "body" : "The scooter went for a total of 45 kms before giving up and I had to push it up the last hill. The voltage then was 42V. It was getting sluggish from about 43-44V. The total trip time was 2.9 hours.",
    "lastSaved" : "2025-12-21T03:18:52Z",
    "endDate" : "2021-07-24T08:36:40Z",
    "id" : "F1E2ACB4-D8D9-4BB9-B29C-355BE7B1107D",
    "source" : "LocoKit",
    "creationDate" : "2025-12-21T03:18:52Z"
  },
  {
    "deleted" : false,
    "startDate" : "2021-07-24T09:02:49Z",
    "body" : "While I was coming home, Anita said she was going to get COVID tested. I though it was for Katherine’s extras work, but it was for Anita. I rode to the testing site to see her there before riding home along the creek.",
    "lastSaved" : "2025-12-21T03:18:52Z",
    "endDate" : "2021-07-24T09:02:49Z",
    "id" : "E010E009-F302-44A8-91A1-269B8D1687EB",
    "source" : "LocoKit",
    "creationDate" : "2025-12-21T03:18:52Z"
  },
  {
    "deleted" : false,
    "startDate" : "2021-07-25T03:21:44Z",
    "body" : "Really windy today",
    "lastSaved" : "2025-12-21T03:18:52Z",
    "endDate" : "2021-07-25T03:21:44Z",
    "id" : "C35F1471-0A4C-4E7B-BA2D-E9D93C3B5573",
    "source" : "LocoKit",
    "creationDate" : "2025-12-21T03:18:52Z"
  },
  {
    "deleted" : false,
    "startDate" : "2021-07-25T07:52:55Z",
    "body" : "Stopped at the usual place at West End when I go for the city ride.",
    "lastSaved" : "2025-12-21T03:18:52Z",
    "endDate" : "2021-07-25T07:52:55Z",
    "id" : "7B1CDEAB-0D3D-44B2-9497-B2CC2B6FB8ED",
    "source" : "LocoKit",
    "creationDate" : "2025-12-21T03:18:52Z"
  },
  {
    "deleted" : false,
    "startDate" : "2021-07-25T08:50:58Z",
    "body" : "I went up past the Roma Street Gardens and on to the RWBH. Then I rode along the footpath through the valley and on into the city. I think next time I will try to get across to Tenerife and follow the river; The Valley is a bit dodgy!\n\nI rode past our favourite hotel at the end of Queen Street. It currently being used as a Quarantine Hotel. There was a bus out front with police everywhere.",
    "lastSaved" : "2025-12-21T03:18:52Z",
    "endDate" : "2021-07-25T08:50:58Z",
    "id" : "25E203D4-A9B2-4DC9-B7FE-957168E72472",
    "source" : "LocoKit",
    "creationDate" : "2025-12-21T03:18:52Z"
  },
  {
    "deleted" : false,
    "startDate" : "2021-07-25T10:09:19Z",
    "body" : "Filled up the WRX for Anita to use for the rest of the week.",
    "lastSaved" : "2025-12-21T03:18:52Z",
    "endDate" : "2021-07-25T10:09:19Z",
    "id" : "8F87F879-1DB1-43F1-BAFA-55D35821B143",
    "source" : "LocoKit",
    "creationDate" : "2025-12-21T03:18:52Z"
  },
  {
    "deleted" : false,
    "startDate" : "2021-07-26T10:26:25Z",
    "body" : "Picked up the Lumos Bicycle Helmet.",
    "lastSaved" : "2025-12-21T03:18:52Z",
    "endDate" : "2021-07-26T10:26:25Z",
    "id" : "A466078A-C58A-4D87-B8FA-53F43DF6B524",
    "source" : "LocoKit",
    "creationDate" : "2025-12-21T03:18:52Z"
  },
  {
    "deleted" : false,
    "startDate" : "2021-07-27T07:18:01Z",
    "body" : "Major Arc stuff up! Looks like it crashed and never came back for most of the day. I can’t believe I never checked it?",
    "lastSaved" : "2025-12-21T03:18:52Z",
    "endDate" : "2021-07-27T07:18:01Z",
    "id" : "D2F1A401-06CD-4D25-97D7-83C61C342D89",
    "source" : "LocoKit",
    "creationDate" : "2025-12-21T03:18:52Z"
  },
  {
    "deleted" : false,
    "startDate" : "2021-07-27T22:49:14Z",
    "body" : "I was upgrading my Apple Watch so had to leave my phone at home for the round trip to Redeemer.\n\nI made a mistake by going onto the freeway this morning, so had to go all the way down to Springwood before backtracking to the school. The roundabout below the school was the worst part. The battery consumption was 16%, so about 4% more than usual.",
    "lastSaved" : "2025-12-21T03:18:52Z",
    "endDate" : "2021-07-27T22:49:14Z",
    "id" : "55BFB101-132F-4D84-8E24-805922EE1B5F",
    "source" : "LocoKit",
    "creationDate" : "2025-12-21T03:18:52Z"
  },
  {
    "deleted" : false,
    "startDate" : "2021-07-29T00:10:14Z",
    "body" : "Dropped the Forester off to have the front left and right window seals and the window washer bottle replaced.",
    "lastSaved" : "2025-12-21T03:18:52Z",
    "endDate" : "2021-07-29T00:10:14Z",
    "id" : "5B92A33F-823A-4244-94B4-CEEA662A4305",
    "source" : "LocoKit",
    "creationDate" : "2025-12-21T03:18:52Z"
  },
  {
    "deleted" : false,
    "startDate" : "2021-07-29T00:33:02Z",
    "body" : "This is the first time I used the new scooter to get myself back home. It’s actually easier to put in the back than the Zero 9 and the Nope bicycle!",
    "lastSaved" : "2025-12-21T03:18:52Z",
    "endDate" : "2021-07-29T00:33:02Z",
    "id" : "890AD234-C106-4EA4-953D-D747B06E2A13",
    "source" : "LocoKit",
    "creationDate" : "2025-12-21T03:18:52Z"
  },
  {
    "deleted" : false,
    "startDate" : "2021-07-29T03:04:38Z",
    "body" : "There were two outside Hudson’s Coffee Shop. The first one didn’t release the helmet so I had to use the second one.",
    "lastSaved" : "2025-12-21T03:18:52Z",
    "endDate" : "2021-07-29T03:04:38Z",
    "id" : "9C2D935E-818C-430F-9177-F7616F90E6C0",
    "source" : "LocoKit",
    "creationDate" : "2025-12-21T03:18:52Z"
  },
  {
    "deleted" : false,
    "startDate" : "2021-07-29T03:23:50Z",
    "body" : "Waiting to see Dr Sharma at a follow-up\nappointment at the QEI, South Brisbane. Made it to the clinic at exactly the appointment time!",
    "lastSaved" : "2025-12-21T03:18:52Z",
    "endDate" : "2021-07-29T03:23:50Z",
    "id" : "703419B4-3B4F-432D-9746-DADDDA7A3C7C",
    "source" : "LocoKit",
    "creationDate" : "2025-12-21T03:18:52Z"
  },
  {
    "deleted" : false,
    "startDate" : "2021-07-30T06:36:02Z",
    "body" : "Hurried home to take Katherine to QYO rehearsals.",
    "lastSaved" : "2025-12-21T03:18:52Z",
    "endDate" : "2021-07-30T06:36:02Z",
    "id" : "CCF40E76-2746-4AA9-9415-780985858428",
    "source" : "LocoKit",
    "creationDate" : "2025-12-21T03:18:52Z"
  },
  {
    "deleted" : false,
    "startDate" : "2021-07-30T07:41:48Z",
    "body" : "Waze took us via the Gateway Bridge! There was a problem on the freeway inbound so this long way round was faster.",
    "lastSaved" : "2025-12-21T03:18:52Z",
    "endDate" : "2021-07-30T07:41:48Z",
    "id" : "CB324145-B6E2-441A-8FC4-E97D15E89109",
    "source" : "LocoKit",
    "creationDate" : "2025-12-21T03:18:52Z"
  },
  {
    "deleted" : false,
    "startDate" : "2021-07-30T08:11:06Z",
    "body" : "I forgot my Apple AirPods at work, so I dropped in to pick them up. I found a tricky spot under the hospital to park; needed the 360 cameras for that one. Anita waited in the car.",
    "lastSaved" : "2025-12-21T03:18:52Z",
    "endDate" : "2021-07-30T08:11:06Z",
    "id" : "22384C3B-6846-46F3-ABA3-4D8D90EE853B",
    "source" : "LocoKit",
    "creationDate" : "2025-12-21T03:18:52Z"
  },
  {
    "deleted" : false,
    "startDate" : "2021-07-30T10:06:23Z",
    "body" : "CEGS had their open day earlier, so we were stuck in their traffic jam long enough that we had to park up the street and walk down to the old museum.",
    "lastSaved" : "2025-12-21T03:18:52Z",
    "endDate" : "2021-07-30T10:06:23Z",
    "id" : "DD34CEE8-61DE-450A-8497-3D7D1BA72464",
    "source" : "LocoKit",
    "creationDate" : "2025-12-21T03:18:52Z"
  },
  {
    "deleted" : false,
    "startDate" : "2021-07-30T11:05:22Z",
    "body" : "Stopped at McDonalds for takeaway",
    "lastSaved" : "2025-12-21T03:18:52Z",
    "endDate" : "2021-07-30T11:05:22Z",
    "id" : "D03AA092-D1D2-4A61-9080-ACCC5F5A6380",
    "source" : "LocoKit",
    "creationDate" : "2025-12-21T03:18:52Z"
  },
  {
    "deleted" : false,
    "startDate" : "2021-07-30T21:15:22Z",
    "body" : "Brisbane is in lockdown for the next three days. I think it will be longer given the rate of infections at the schools. A medical student had acquired COVID from a traveller somehow and then transferred it to a student from Indooroopilly State High School. Other schools were brought into the infections through a karate school at the Ironside State School.",
    "lastSaved" : "2025-12-21T03:18:52Z",
    "endDate" : "2021-07-30T21:15:22Z",
    "id" : "EBFAF9BA-556E-4620-8676-CB2FC4BFD263",
    "source" : "LocoKit",
    "creationDate" : "2025-12-21T03:18:52Z"
  }
]