[
  {
    "locality" : "South Brisbane",
    "rtreeId" : 12,
    "visitCount" : 138,
    "source" : "LocoKit",
    "radiusSD" : 16.823393429989498,
    "id" : "6AD67257-96BA-4DB9-AED5-69CAC6F6E9DF",
    "secondsFromGMT" : 36000,
    "longitude" : 153.0244552085161,
    "name" : "Epicurious At South Bank",
    "isStale" : false,
    "lastSaved" : "2025-12-26T20:41:11Z",
    "visitDays" : 137,
    "streetAddress" : "445A Stanley St",
    "lastVisitDate" : "2025-06-16T01:11:28Z",
    "countryCode" : "au",
    "radiusMean" : 19.35909130950856,
    "latitude" : -27.480126724131118
  },
  {
    "locality" : "South Brisbane",
    "rtreeId" : 27,
    "visitCount" : 45,
    "source" : "LocoKit",
    "radiusSD" : 32.608301530862676,
    "id" : "673AA4F2-7E9D-45E1-BC7E-68C1C2ADB6F7",
    "secondsFromGMT" : 36000,
    "longitude" : 153.02875588477173,
    "name" : "Mater Potter Building",
    "isStale" : false,
    "lastSaved" : "2025-12-27T00:16:11Z",
    "visitDays" : 39,
    "foursquarePlaceId" : "4e0d1c03c65ba20da213b536",
    "streetAddress" : "Mater Children's Private Brisbane",
    "lastVisitDate" : "2021-04-19T01:23:26Z",
    "countryCode" : "au",
    "radiusMean" : 78.59569970187438,
    "latitude" : -27.48689665520983
  },
  {
    "locality" : "Woolloongabba",
    "rtreeId" : 28,
    "visitCount" : 49,
    "source" : "LocoKit",
    "radiusSD" : 14.279669677700998,
    "id" : "6291C209-3FEB-4057-98BA-04FFAE5A4489",
    "secondsFromGMT" : 36000,
    "longitude" : 153.03717886434205,
    "name" : "John French Motors",
    "isStale" : false,
    "lastSaved" : "2025-12-26T20:39:57Z",
    "visitDays" : 34,
    "foursquarePlaceId" : "4d81afec7252a1cd1d4d9f5d",
    "streetAddress" : "21 Balaclava St",
    "lastVisitDate" : "2023-10-17T22:50:49Z",
    "countryCode" : "au",
    "radiusMean" : 12.690222359063203,
    "latitude" : -27.490275214851874
  },
  {
    "locality" : "Carindale",
    "rtreeId" : 45,
    "visitCount" : 40,
    "source" : "LocoKit",
    "radiusSD" : 5.918901530544512,
    "id" : "6057C0F9-77D5-4058-894B-BE12A222C770",
    "secondsFromGMT" : 36000,
    "longitude" : 153.11620649533847,
    "name" : "KFC",
    "isStale" : false,
    "lastSaved" : "2025-12-27T00:16:11Z",
    "visitDays" : 40,
    "foursquarePlaceId" : "4c109ff0ce57c928602b82d2",
    "streetAddress" : "1294 Old Cleveland Rd",
    "lastVisitDate" : "2020-12-26T07:48:53Z",
    "countryCode" : "au",
    "radiusMean" : 15.178023427567869,
    "latitude" : -27.50205033012765
  },
  {
    "locality" : "Rochedale",
    "rtreeId" : 77,
    "visitCount" : 131,
    "source" : "LocoKit",
    "radiusSD" : 13.394581079893785,
    "id" : "682D84D7-E388-456A-8C6D-D17772622857",
    "secondsFromGMT" : 36000,
    "longitude" : 153.1131330713167,
    "name" : "Coles, Rochedale",
    "isStale" : false,
    "lastSaved" : "2025-12-21T23:37:39Z",
    "visitDays" : 127,
    "streetAddress" : "31 West St",
    "lastVisitDate" : "2025-12-20T06:16:51Z",
    "countryCode" : "au",
    "radiusMean" : 38.25651779298855,
    "latitude" : -27.577856498545025
  },
  {
    "locality" : "Upper Mount Gravatt",
    "rtreeId" : 88,
    "visitCount" : 10,
    "source" : "LocoKit",
    "radiusSD" : 0.012996455243645014,
    "id" : "6AE6C2AA-2BF3-47CB-AAB6-8454A14B3DD2",
    "secondsFromGMT" : 36000,
    "longitude" : 153.08385035211822,
    "name" : "Moves",
    "isStale" : false,
    "lastSaved" : "2025-12-21T06:18:45Z",
    "visitDays" : 10,
    "streetAddress" : "Westfield Mt Gravatt",
    "lastVisitDate" : "2016-06-26T04:20:58Z",
    "countryCode" : "au",
    "radiusMean" : 8,
    "latitude" : -27.563231145221682
  },
  {
    "streetAddress" : "239 Shore St N",
    "visitDays" : 33,
    "latitude" : -27.51040411095262,
    "longitude" : 153.28976551868612,
    "rtreeId" : 92,
    "source" : "LocoKit",
    "visitCount" : 35,
    "lastSaved" : "2025-12-21T06:18:48Z",
    "id" : "64EC4CF3-A8CD-45DE-B161-BAC581962010",
    "radiusMean" : 14.735514845240234,
    "isStale" : false,
    "secondsFromGMT" : 36000,
    "name" : "Lighthouse Bar And Cafe",
    "lastVisitDate" : "2025-07-13T08:13:01Z",
    "radiusSD" : 13.22657311723675
  },
  {
    "streetAddress" : "Greenslopes Private Hospital",
    "locality" : "Greenslopes",
    "visitDays" : 10,
    "latitude" : -27.51285366879999,
    "longitude" : 153.04575090690003,
    "rtreeId" : 117,
    "source" : "LocoKit",
    "visitCount" : 11,
    "lastSaved" : "2025-12-26T20:48:25Z",
    "id" : "68FD6E9D-6D4F-4A4F-8AA0-E4FBC3109EBE",
    "radiusMean" : 8,
    "isStale" : false,
    "secondsFromGMT" : 36000,
    "countryCode" : "au",
    "name" : "Ward 11",
    "radiusSD" : 4.233231745205801e-25,
    "lastVisitDate" : "2015-11-12T01:27:10Z"
  },
  {
    "streetAddress" : "42 Duntreath St",
    "visitDays" : 4,
    "latitude" : -27.418704418346206,
    "longitude" : 152.9436149353724,
    "rtreeId" : 143,
    "source" : "LocoKit",
    "visitCount" : 6,
    "lastSaved" : "2025-12-21T06:48:04Z",
    "id" : "64892933-F3CE-40E5-9320-D214DEAF9680",
    "radiusMean" : 8,
    "isStale" : false,
    "secondsFromGMT" : 36000,
    "name" : "Grannies place",
    "lastVisitDate" : "2018-08-05T02:22:38Z",
    "radiusSD" : 1.517464150714543
  },
  {
    "radiusMean" : 19.62461814816758,
    "lastSaved" : "2025-12-21T07:36:13Z",
    "name" : "Hog's Breath Cafe",
    "streetAddress" : "Raby Bay Harbour Park",
    "longitude" : 153.26793317564835,
    "radiusSD" : 4.277818720522431,
    "visitCount" : 9,
    "latitude" : -27.5240353325898,
    "secondsFromGMT" : 36000,
    "rtreeId" : 168,
    "source" : "LocoKit",
    "visitDays" : 9,
    "isStale" : false,
    "id" : "65EA9878-EDBE-4A59-944F-1BDF4365689E",
    "lastVisitDate" : "2025-10-17T23:25:29Z"
  },
  {
    "radiusMean" : 28.976771126763285,
    "lastSaved" : "2025-12-21T07:36:14Z",
    "name" : "Pet City",
    "streetAddress" : "224 Wishart Rd",
    "longitude" : 153.0928428219834,
    "radiusSD" : 11.693381389800354,
    "visitCount" : 12,
    "latitude" : -27.546628810296472,
    "secondsFromGMT" : 36000,
    "rtreeId" : 178,
    "foursquarePlaceId" : "4ba34ec6f964a520823438e3",
    "countryCode" : "au",
    "locality" : "Wishart",
    "source" : "LocoKit",
    "isStale" : false,
    "visitDays" : 12,
    "id" : "6095B495-B43E-4D0E-AD43-B9C4C427C383",
    "lastVisitDate" : "2024-05-11T04:18:58Z"
  },
  {
    "radiusMean" : 12.186555500946517,
    "lastSaved" : "2025-12-26T20:39:59Z",
    "name" : "Officeworks",
    "streetAddress" : "1A Reis St",
    "longitude" : 153.03499414053783,
    "radiusSD" : 5.700875855962079,
    "visitCount" : 10,
    "latitude" : -27.49494288354305,
    "secondsFromGMT" : 36000,
    "rtreeId" : 181,
    "foursquarePlaceId" : "4b1f1fcef964a520302424e3",
    "countryCode" : "au",
    "locality" : "Woolloongabba",
    "source" : "LocoKit",
    "isStale" : false,
    "visitDays" : 10,
    "id" : "6D1A4E1B-06FB-4FF7-9D1C-D32F6F4FA15C",
    "lastVisitDate" : "2024-07-15T22:27:49Z"
  },
  {
    "radiusMean" : 53.115152509023694,
    "lastSaved" : "2025-12-21T20:21:07Z",
    "name" : "Redeemer MPC Building",
    "streetAddress" : "Redeemer Lutheran College",
    "longitude" : 153.12398494690666,
    "radiusSD" : 20.24511757885995,
    "visitCount" : 7,
    "latitude" : -27.583918740148818,
    "secondsFromGMT" : 36000,
    "rtreeId" : 186,
    "countryCode" : "au",
    "locality" : "Rochedale",
    "source" : "LocoKit",
    "isStale" : false,
    "visitDays" : 7,
    "id" : "6BC5E08D-F0D7-4A21-96D0-2E5A1D870E22",
    "lastVisitDate" : "2020-02-22T07:54:50Z"
  },
  {
    "radiusMean" : 8,
    "lastSaved" : "2025-12-21T07:36:20Z",
    "name" : "Sunseeker Lodge",
    "longitude" : 153.1097061666667,
    "radiusSD" : 1.07995246563922e-25,
    "visitCount" : 6,
    "latitude" : -26.409537460000006,
    "rtreeId" : 211,
    "foursquarePlaceId" : "4df1bb3dd1649c8a28dba5e3",
    "source" : "LocoKit",
    "visitDays" : 2,
    "isStale" : false,
    "id" : "6DAA43C1-3E13-4CAB-8147-50BC96165637",
    "lastVisitDate" : "2014-06-08T08:32:57Z"
  },
  {
    "radiusMean" : 8,
    "lastSaved" : "2025-12-26T20:42:17Z",
    "name" : "Des O'Callaghan Auditorium",
    "streetAddress" : "Mater Children's Private Brisbane",
    "longitude" : 153.0282920928,
    "radiusSD" : 0,
    "visitCount" : 6,
    "latitude" : -27.4863414232,
    "secondsFromGMT" : 36000,
    "rtreeId" : 212,
    "countryCode" : "au",
    "locality" : "South Brisbane",
    "source" : "LocoKit",
    "isStale" : false,
    "visitDays" : 6,
    "id" : "667E73C0-66D2-4B84-99A7-707486273458",
    "lastVisitDate" : "2015-03-25T01:12:38Z"
  },
  {
    "radiusMean" : 8,
    "lastSaved" : "2025-12-21T07:36:22Z",
    "name" : "Bus Stop 74",
    "streetAddress" : "228 Wishart Rd",
    "longitude" : 153.09310470750802,
    "radiusSD" : 1.07995246563922e-25,
    "visitCount" : 6,
    "latitude" : -27.547355289037814,
    "secondsFromGMT" : 36000,
    "rtreeId" : 226,
    "countryCode" : "au",
    "locality" : "Wishart",
    "source" : "LocoKit",
    "isStale" : false,
    "visitDays" : 6,
    "id" : "6324DBC5-FADE-4E13-AD9A-9B7A41ACF48D",
    "lastVisitDate" : "2018-06-06T21:06:47Z"
  },
  {
    "longitude" : 135.75963867194065,
    "foursquarePlaceId" : "4b62cc04f964a52017532ae3",
    "isStale" : false,
    "visitDays" : 3,
    "id" : "6B4B783D-FF38-4835-9A1D-EF0FE9BA2D47",
    "lastVisitDate" : "2019-12-07T09:01:03Z",
    "visitCount" : 4,
    "name" : "Hotel Granvia Kyoto (ホテルグランヴィア京都)",
    "radiusSD" : 51.78297103181552,
    "latitude" : 34.985437754974186,
    "radiusMean" : 67.0891899079418,
    "rtreeId" : 242,
    "lastSaved" : "2025-12-21T07:36:25Z",
    "source" : "LocoKit"
  },
  {
    "longitude" : 153.01798845341517,
    "foursquarePlaceId" : "4b06fdfdf964a520f1f422e3",
    "countryCode" : "au",
    "isStale" : false,
    "visitDays" : 5,
    "streetAddress" : "Queensland Museum",
    "id" : "660FEA59-A0C8-4B28-8765-F494EE541359",
    "lastVisitDate" : "2024-11-22T08:31:13Z",
    "secondsFromGMT" : 36000,
    "name" : "Queensland Museum",
    "visitCount" : 6,
    "radiusSD" : 87.6870649068805,
    "latitude" : -27.47315080030908,
    "locality" : "South Brisbane",
    "radiusMean" : 51.01722594476129,
    "lastSaved" : "2025-12-26T20:42:18Z",
    "rtreeId" : 256,
    "source" : "LocoKit"
  },
  {
    "foursquarePlaceId" : "4b05873bf964a520498622e3",
    "secondsFromGMT" : 36000,
    "lastVisitDate" : "2017-12-09T03:19:48Z",
    "radiusSD" : 5.44953077500174e-26,
    "id" : "6E86C302-D767-40A3-92F1-6A53AC667459",
    "name" : "David Jones",
    "source" : "LocoKit",
    "lastSaved" : "2025-12-21T07:36:28Z",
    "rtreeId" : 258,
    "latitude" : -27.562156142656576,
    "visitCount" : 5,
    "longitude" : 153.0809211730957,
    "locality" : "Upper Mount Gravatt",
    "streetAddress" : "Westfield Mt Gravatt",
    "isStale" : false,
    "countryCode" : "au",
    "radiusMean" : 8,
    "visitDays" : 5
  },
  {
    "radiusSD" : 7.335218014362286,
    "id" : "64B151C5-D65B-4EE1-883C-BB874574134D",
    "name" : "Blind Freddy Electric Bicycles",
    "source" : "LocoKit",
    "lastSaved" : "2025-12-21T07:36:30Z",
    "rtreeId" : 267,
    "latitude" : -27.327312995750393,
    "visitCount" : 5,
    "longitude" : 152.97998495316108,
    "isStale" : false,
    "radiusMean" : 19.035439075090355,
    "lastVisitDate" : "2019-07-27T02:36:38Z",
    "visitDays" : 5
  },
  {
    "source" : "LocoKit",
    "lastSaved" : "2025-12-26T20:41:07Z",
    "streetAddress" : "Queensland Children’s Hospital",
    "radiusSD" : 18.56830248805147,
    "latitude" : -27.48363105353316,
    "visitCount" : 6,
    "id" : "6A75B0A0-FA69-4AD5-BB3F-B47D9315A2E6",
    "countryCode" : "au",
    "secondsFromGMT" : 36000,
    "longitude" : 153.0266553363483,
    "locality" : "South Brisbane",
    "radiusMean" : 16.498982025402043,
    "rtreeId" : 275,
    "visitDays" : 5,
    "lastVisitDate" : "2017-08-23T09:17:59Z",
    "isStale" : false,
    "name" : "Lady Cilento Children's Hospital School"
  },
  {
    "source" : "LocoKit",
    "lastSaved" : "2025-12-30T13:24:13Z",
    "streetAddress" : "Gold Coast Convention and Exhibition Centre",
    "radiusSD" : 0,
    "latitude" : -28.027910552547006,
    "visitCount" : 5,
    "id" : "6AF12DB2-7BEE-4AC3-9AD5-8C71F8EEB9BD",
    "countryCode" : "au",
    "secondsFromGMT" : 36000,
    "longitude" : 153.42938519913,
    "locality" : "Broadbeach",
    "radiusMean" : 8,
    "rtreeId" : 285,
    "visitDays" : 3,
    "lastVisitDate" : "2016-04-10T05:40:42Z",
    "isStale" : false,
    "name" : "Supanova"
  },
  {
    "source" : "LocoKit",
    "lastSaved" : "2025-12-21T07:36:43Z",
    "visitCount" : 4,
    "radiusSD" : 1.1053665889840106e-25,
    "latitude" : -28.231907765200003,
    "id" : "64156AED-1E8A-4BD4-86A0-D11C9CCE7735",
    "longitude" : 153.1261477231,
    "rtreeId" : 320,
    "radiusMean" : 8,
    "lastVisitDate" : "2014-04-20T02:26:45Z",
    "visitDays" : 2,
    "isStale" : false,
    "name" : "Morans Falls Lookout"
  },
  {
    "source" : "LocoKit",
    "lastSaved" : "2025-12-21T07:36:52Z",
    "visitCount" : 4,
    "radiusSD" : 2.4656386412407776,
    "latitude" : -27.598588138928374,
    "id" : "641B8388-E7A0-47CD-AF63-8F5FC8183179",
    "longitude" : 153.0883379693098,
    "rtreeId" : 358,
    "radiusMean" : 8,
    "lastVisitDate" : "2020-01-19T22:58:59Z",
    "visitDays" : 4,
    "isStale" : false,
    "name" : "Katherine’s School Friend"
  },
  {
    "source" : "LocoKit",
    "lastSaved" : "2025-12-26T20:42:26Z",
    "streetAddress" : "Brisbane River",
    "radiusSD" : 9.651059198509618,
    "latitude" : -27.466789172185802,
    "visitCount" : 3,
    "id" : "6697C761-1BED-420D-8922-A0EF9BC38C7C",
    "countryCode" : "au",
    "secondsFromGMT" : 36000,
    "longitude" : 153.03136603302988,
    "locality" : "Brisbane",
    "radiusMean" : 17.66507511870358,
    "rtreeId" : 375,
    "visitDays" : 3,
    "lastVisitDate" : "2019-10-05T06:33:38Z",
    "isStale" : false,
    "name" : "Riverside Ferry terminal "
  },
  {
    "source" : "LocoKit",
    "lastSaved" : "2025-12-21T07:36:56Z",
    "visitCount" : 3,
    "radiusSD" : 3.8468377221771064,
    "latitude" : -27.226207531800032,
    "id" : "61F97370-1EDD-44FC-A1FA-3819AA7BDDC3",
    "foursquarePlaceId" : "4b908256f964a520db8d33e3",
    "longitude" : 153.11483158958671,
    "rtreeId" : 377,
    "radiusMean" : 8,
    "lastVisitDate" : "2014-01-26T22:45:20Z",
    "visitDays" : 2,
    "isStale" : false,
    "name" : "The Coffee Club"
  },
  {
    "source" : "LocoKit",
    "lastSaved" : "2025-12-21T08:08:31Z",
    "streetAddress" : "Westfield Mt Gravatt",
    "radiusSD" : 11.841606834799483,
    "latitude" : -27.56218003738713,
    "visitCount" : 2,
    "id" : "6A32A2D3-6CB2-4B8E-B1A6-9FC1FC84B484",
    "foursquarePlaceId" : "5b257ce56336be002c31fe7f",
    "countryCode" : "au",
    "secondsFromGMT" : 36000,
    "longitude" : 153.08069925379763,
    "locality" : "Upper Mount Gravatt",
    "radiusMean" : 11.027221265742629,
    "rtreeId" : 458,
    "visitDays" : 2,
    "lastVisitDate" : "2020-06-20T03:57:35Z",
    "isStale" : false,
    "name" : "Motto Motto Japanese Kitchen"
  },
  {
    "source" : "LocoKit",
    "lastSaved" : "2025-12-21T08:08:34Z",
    "streetAddress" : "Currumbin",
    "radiusSD" : 2.897928389401821,
    "latitude" : -28.135621124426443,
    "visitCount" : 2,
    "id" : "65318327-01CE-4A6A-B628-8B616A0AF9FE",
    "longitude" : 153.48462886991516,
    "rtreeId" : 462,
    "secondsFromGMT" : 36000,
    "radiusMean" : 30.213715722820286,
    "lastVisitDate" : "2020-01-05T06:12:33Z",
    "visitDays" : 1,
    "isStale" : false,
    "name" : "Wallaby Encounters"
  },
  {
    "latitude" : 35.642650265132005,
    "rtreeId" : 486,
    "foursquarePlaceId" : "4b56f0fef964a520042028e3",
    "longitude" : 139.28281943006525,
    "visitDays" : 1,
    "visitCount" : 2,
    "isStale" : false,
    "name" : "Takao Station (高尾駅)",
    "lastSaved" : "2025-12-21T08:08:53Z",
    "source" : "LocoKit",
    "id" : "6E3EFA11-D581-43EF-BC04-9D85A6E16243",
    "radiusMean" : 33.37893062145482,
    "lastVisitDate" : "2019-12-03T07:39:38Z",
    "radiusSD" : 34.69272120954045
  },
  {
    "latitude" : -27.484981568298295,
    "rtreeId" : 494,
    "foursquarePlaceId" : "4b058735f964a520768422e3",
    "longitude" : 152.9590632579907,
    "visitDays" : 1,
    "visitCount" : 2,
    "isStale" : false,
    "name" : "Mount Coot-tha Lookout",
    "lastSaved" : "2025-12-21T08:09:00Z",
    "source" : "LocoKit",
    "id" : "6E9AD377-BA95-4FB5-ABA4-F212F6D675DB",
    "radiusMean" : 23.944917008263605,
    "lastVisitDate" : "2019-11-06T12:59:57Z",
    "radiusSD" : 2.0605508996791873
  },
  {
    "lastVisitDate" : "2013-11-23T04:57:50Z",
    "latitude" : -27.5625003743762,
    "rtreeId" : 505,
    "secondsFromGMT" : 36000,
    "streetAddress" : "Westfield Mt Gravatt",
    "longitude" : 153.0820809239426,
    "foursquarePlaceId" : "4ba436d3f964a520a58c38e3",
    "visitDays" : 1,
    "visitCount" : 2,
    "isStale" : false,
    "name" : "Westfield Garden City",
    "locality" : "Upper Mount Gravatt",
    "source" : "LocoKit",
    "lastSaved" : "2025-12-21T08:09:08Z",
    "id" : "6EC84A1C-8AC3-447A-9869-3F7FDC44B61E",
    "radiusMean" : 8,
    "radiusSD" : 0,
    "countryCode" : "au"
  },
  {
    "latitude" : -27.732630782455423,
    "rtreeId" : 525,
    "foursquarePlaceId" : "4b553352f964a5206fde27e3",
    "longitude" : 153.228120803833,
    "visitDays" : 2,
    "visitCount" : 2,
    "isStale" : false,
    "name" : "BP Connect",
    "lastSaved" : "2025-12-21T15:52:39Z",
    "source" : "LocoKit",
    "id" : "6093C74D-B767-4AA5-9A5A-FC38EF585B91",
    "radiusMean" : 8,
    "lastVisitDate" : "2015-05-09T03:41:24Z",
    "radiusSD" : 0
  },
  {
    "latitude" : -28.2336303566,
    "rtreeId" : 553,
    "secondsFromGMT" : 36000,
    "streetAddress" : "Border Track Great Walk",
    "longitude" : 153.13968612419998,
    "visitDays" : 2,
    "visitCount" : 2,
    "isStale" : false,
    "name" : "Treetop walk",
    "lastSaved" : "2025-12-21T15:52:42Z",
    "source" : "LocoKit",
    "id" : "6FB9EFAC-ECEE-4B1A-9093-E27D4B6F80C6",
    "radiusMean" : 8,
    "lastVisitDate" : "2017-01-08T01:49:23Z",
    "radiusSD" : 0
  },
  {
    "lastVisitDate" : "2020-07-11T04:55:49Z",
    "latitude" : -27.47226737195466,
    "rtreeId" : 582,
    "secondsFromGMT" : 36000,
    "streetAddress" : "City Botanic Gardens",
    "longitude" : 153.0307833596363,
    "foursquarePlaceId" : "4f2340f8e4b0d609c552f30d",
    "visitDays" : 2,
    "visitCount" : 2,
    "isStale" : false,
    "name" : "Gardens Point Boat Harbour",
    "locality" : "Brisbane",
    "source" : "LocoKit",
    "lastSaved" : "2025-12-26T20:43:38Z",
    "id" : "6BCA5834-9965-464E-880E-5E1C60E1EA0E",
    "radiusMean" : 22.722039015209734,
    "radiusSD" : 11.098929920730534,
    "countryCode" : "au"
  },
  {
    "latitude" : -27.619176178067725,
    "rtreeId" : 588,
    "secondsFromGMT" : 36000,
    "streetAddress" : "1 Compton Rd",
    "longitude" : 153.11402842529372,
    "visitDays" : 1,
    "visitCount" : 2,
    "isStale" : false,
    "name" : "Officeworks, Underwood",
    "lastSaved" : "2025-12-21T15:52:47Z",
    "source" : "LocoKit",
    "id" : "600F0CED-8746-47B4-86C7-CE437027AFA7",
    "radiusMean" : 14.419613127556335,
    "lastVisitDate" : "2018-10-16T07:18:54Z",
    "radiusSD" : 7.241307039665243
  },
  {
    "foursquarePlaceId" : "4fbc877fe4b04e551e2f81c7",
    "visitCount" : 2,
    "radiusSD" : 0.4034468533509742,
    "name" : "Coffs Coast Regional Park",
    "isStale" : false,
    "latitude" : -30.265869024475677,
    "lastSaved" : "2025-12-21T15:52:47Z",
    "source" : "LocoKit",
    "lastVisitDate" : "2016-01-08T06:48:03Z",
    "longitude" : 153.13940634140235,
    "radiusMean" : 15.026315811442995,
    "rtreeId" : 590,
    "id" : "631852C9-CCD4-4C92-9281-7CF7E52587D8",
    "visitDays" : 1
  },
  {
    "foursquarePlaceId" : "5b039ab39ba3e5002cb85dde",
    "name" : "Sushi Edo",
    "radiusSD" : 1.6157130485056166,
    "streetAddress" : "Westfield Mt Gravatt",
    "isStale" : false,
    "latitude" : -27.562262674533795,
    "lastSaved" : "2025-12-21T15:52:47Z",
    "source" : "LocoKit",
    "visitCount" : 2,
    "lastVisitDate" : "2019-01-23T01:30:07Z",
    "longitude" : 153.08022967608844,
    "secondsFromGMT" : 36000,
    "radiusMean" : 14.555262727753039,
    "rtreeId" : 591,
    "id" : "647EB156-9859-450D-8F18-B14A3A3D3C51",
    "visitDays" : 2,
    "locality" : "Upper Mount Gravatt",
    "countryCode" : "au"
  },
  {
    "name" : "Riviera",
    "radiusSD" : 9.073954182503353,
    "streetAddress" : "50 Lower River Tce",
    "isStale" : false,
    "latitude" : -27.483001954382978,
    "lastSaved" : "2025-12-26T20:43:36Z",
    "source" : "LocoKit",
    "visitCount" : 2,
    "lastVisitDate" : "2016-06-22T09:46:19Z",
    "longitude" : 153.030186579423,
    "secondsFromGMT" : 36000,
    "radiusMean" : 8,
    "rtreeId" : 594,
    "id" : "69579695-987C-4E2F-8CB4-A63D281958B1",
    "visitDays" : 2,
    "locality" : "South Brisbane",
    "countryCode" : "au"
  },
  {
    "name" : "Julie",
    "radiusSD" : 4.124413574748622,
    "isStale" : false,
    "streetAddress" : "35 White St",
    "latitude" : -27.52001011670728,
    "lastSaved" : "2025-12-21T15:52:57Z",
    "source" : "LocoKit",
    "visitCount" : 4,
    "lastVisitDate" : "2025-01-18T00:17:46Z",
    "longitude" : 152.9822858193414,
    "secondsFromGMT" : 36000,
    "radiusMean" : 8.32234122204485,
    "rtreeId" : 660,
    "id" : "6641294E-A988-4E6F-8015-88318B0EAC67",
    "visitDays" : 4
  },
  {
    "latitude" : -27.468556109236903,
    "visitCount" : 1,
    "foursquarePlaceId" : "53dc4b8c498e2c14889a0d73",
    "radiusMean" : 8,
    "name" : "Wellington Point water front",
    "lastVisitDate" : "2020-01-01T06:08:02Z",
    "visitDays" : 1,
    "source" : "LocoKit",
    "rtreeId" : 719,
    "radiusSD" : 1.0810561078440666,
    "lastSaved" : "2025-12-21T15:53:06Z",
    "id" : "6C509224-35FE-4132-8E6B-47AFD78FBD07",
    "longitude" : 153.23933115651516,
    "isStale" : false
  },
  {
    "latitude" : 35.45367840395542,
    "visitCount" : 1,
    "foursquarePlaceId" : "4b5abe23f964a520ecd228e3",
    "radiusMean" : 8,
    "name" : "Yokohama World Porters (横浜ワールドポーターズ)",
    "lastVisitDate" : "2019-12-14T06:48:48Z",
    "visitDays" : 1,
    "source" : "LocoKit",
    "rtreeId" : 735,
    "radiusSD" : 0.608520346760358,
    "lastSaved" : "2025-12-21T15:53:08Z",
    "id" : "6DD586CE-08F5-475D-BD8E-19B2C8182342",
    "longitude" : 139.63834182012044,
    "isStale" : false
  },
  {
    "latitude" : 34.39391982339612,
    "visitCount" : 1,
    "foursquarePlaceId" : "4b811863f964a520929630e3",
    "radiusMean" : 8,
    "name" : "Hatchobori Station (八丁堀電停)",
    "lastVisitDate" : "2019-12-11T11:12:08Z",
    "visitDays" : 1,
    "source" : "LocoKit",
    "rtreeId" : 744,
    "radiusSD" : 2.436437956341466,
    "lastSaved" : "2025-12-21T15:53:10Z",
    "id" : "65767342-C4BE-4CCC-BC23-5341E7F5864E",
    "longitude" : 132.46289420564946,
    "isStale" : false
  },
  {
    "latitude" : 34.27938309359184,
    "visitCount" : 1,
    "foursquarePlaceId" : "4dc10d2f22713750ba73c1cb",
    "radiusMean" : 8,
    "name" : "Shishiiwa Ropeway Station (宮島ロープウエー 獅子岩駅)",
    "lastVisitDate" : "2019-12-09T02:50:19Z",
    "visitDays" : 1,
    "source" : "LocoKit",
    "rtreeId" : 762,
    "radiusSD" : 2.0960357349058705,
    "lastSaved" : "2025-12-21T15:53:12Z",
    "id" : "6AA7D9A3-0AF8-4F72-8056-B47A0F61C8A7",
    "longitude" : 132.32494725558746,
    "isStale" : false
  },
  {
    "latitude" : 34.96688494517353,
    "visitCount" : 1,
    "foursquarePlaceId" : "4b7bfa11f964a520b1762fe3",
    "radiusMean" : 8,
    "name" : "Inari Station (稲荷駅)",
    "lastVisitDate" : "2019-12-06T08:15:07Z",
    "visitDays" : 1,
    "source" : "LocoKit",
    "rtreeId" : 779,
    "radiusSD" : 4.165920488901372,
    "lastSaved" : "2025-12-21T15:53:16Z",
    "id" : "64D56F6C-2CA1-43CF-BEB4-84CDD7448DC5",
    "longitude" : 135.77068251535397,
    "isStale" : false
  },
  {
    "latitude" : 35.642260685246626,
    "source" : "LocoKit",
    "foursquarePlaceId" : "4b5bafabf964a520f70f29e3",
    "id" : "686D969D-9D0E-46BE-912A-FD572619CA1E",
    "longitude" : 139.28460359793675,
    "visitCount" : 1,
    "radiusMean" : 8,
    "rtreeId" : 796,
    "name" : "Gourmet City (グルメシティ 高尾店)",
    "isStale" : false,
    "radiusSD" : 1.9278966137128426,
    "lastSaved" : "2025-12-21T15:53:19Z",
    "lastVisitDate" : "2019-12-03T02:12:18Z",
    "visitDays" : 1
  },
  {
    "countryCode" : "au",
    "latitude" : -27.56335806068989,
    "source" : "LocoKit",
    "longitude" : 153.08354179774528,
    "id" : "6C933439-1CBD-4A1D-9061-4A44648CF34D",
    "foursquarePlaceId" : "4ca3d4471ee76dcbd1b9fcdd",
    "locality" : "Upper Mount Gravatt",
    "streetAddress" : "Westfield Mt Gravatt",
    "visitCount" : 1,
    "secondsFromGMT" : 36000,
    "radiusMean" : 8.276398505561813,
    "rtreeId" : 820,
    "name" : "Origin Kebabs",
    "isStale" : false,
    "radiusSD" : 11.05992410312582,
    "lastSaved" : "2025-12-21T15:53:24Z",
    "lastVisitDate" : "2019-11-04T02:02:10Z",
    "visitDays" : 1
  },
  {
    "latitude" : -27.33312119211191,
    "source" : "LocoKit",
    "longitude" : 152.7711285156321,
    "id" : "618B129B-262A-4251-9BA6-8BECE6875760",
    "foursquarePlaceId" : "4e112103fa769d21e9eb0091",
    "streetAddress" : "1812 Mount Glorious Rd",
    "visitCount" : 1,
    "secondsFromGMT" : 36000,
    "radiusMean" : 8,
    "rtreeId" : 879,
    "isStale" : false,
    "name" : "Mount Glorious Restaurant And Cafe",
    "radiusSD" : 0,
    "lastSaved" : "2025-12-21T15:53:36Z",
    "lastVisitDate" : "2013-12-28T03:49:30Z",
    "visitDays" : 1
  },
  {
    "latitude" : -27.90743998705933,
    "source" : "LocoKit",
    "foursquarePlaceId" : "4b058736f964a520e38422e3",
    "id" : "657028CE-4C6B-49DD-B52F-93ED6DADB4C1",
    "longitude" : 153.31264793872828,
    "visitCount" : 1,
    "radiusMean" : 8,
    "rtreeId" : 883,
    "name" : "Warner Bros. Movie World",
    "isStale" : false,
    "radiusSD" : 0,
    "lastSaved" : "2025-12-21T15:53:36Z",
    "lastVisitDate" : "2013-12-14T07:29:32Z",
    "visitDays" : 1
  },
  {
    "latitude" : -30.26653,
    "source" : "LocoKit",
    "longitude" : 153.109439,
    "id" : "6BB14582-F50E-4053-BC02-136C69CDF186",
    "foursquarePlaceId" : "5144f8bde4b0df5d57027370",
    "streetAddress" : "171 Sealy Lookout Dr",
    "visitCount" : 1,
    "secondsFromGMT" : 39600,
    "radiusMean" : 8,
    "rtreeId" : 891,
    "isStale" : false,
    "name" : "Forest Sky Pier",
    "radiusSD" : 0,
    "lastSaved" : "2025-12-21T15:53:38Z",
    "lastVisitDate" : "2014-01-11T23:22:41Z",
    "visitDays" : 1
  },
  {
    "countryCode" : "au",
    "latitude" : -27.412658254838746,
    "source" : "LocoKit",
    "longitude" : 153.01225397816202,
    "id" : "6695673A-6C16-4994-9FEA-B459DA74A20B",
    "foursquarePlaceId" : "50a06b5ae4b0b72b9a283498",
    "locality" : "Stafford",
    "streetAddress" : "Stafford City Shopping Centre",
    "visitCount" : 1,
    "secondsFromGMT" : 36000,
    "radiusMean" : 8,
    "rtreeId" : 912,
    "name" : "Fong Yong Chinese Takeaway",
    "isStale" : false,
    "radiusSD" : 3.2926616563965863,
    "lastSaved" : "2025-12-24T05:19:27Z",
    "lastVisitDate" : "2014-05-18T04:07:44Z",
    "visitDays" : 1
  },
  {
    "latitude" : -26.433247637199994,
    "source" : "LocoKit",
    "longitude" : 153.0166519501,
    "id" : "648B0697-CC29-42AE-B62F-DB3E38883E77",
    "visitCount" : 1,
    "radiusMean" : 8,
    "rtreeId" : 917,
    "name" : "Boys Town Art Union",
    "isStale" : false,
    "radiusSD" : 0,
    "lastSaved" : "2025-12-21T15:53:43Z",
    "lastVisitDate" : "2014-06-08T04:17:14Z",
    "visitDays" : 1
  },
  {
    "latitude" : -26.405752,
    "source" : "LocoKit",
    "foursquarePlaceId" : "5392b6fd498e65d34f19b7db",
    "id" : "68C0CA8A-DDC3-4E0A-8EE0-AEEA0CF6763C",
    "longitude" : 153.11053000000004,
    "visitCount" : 1,
    "radiusMean" : 8,
    "rtreeId" : 919,
    "name" : "Off The Hook Fish & Chips",
    "isStale" : false,
    "radiusSD" : 0,
    "lastSaved" : "2025-12-21T15:53:43Z",
    "lastVisitDate" : "2014-06-07T06:47:12Z",
    "visitDays" : 1
  },
  {
    "rtreeId" : 924,
    "latitude" : -27.3942958068464,
    "radiusMean" : 8,
    "streetAddress" : "101 Flockton St",
    "visitDays" : 1,
    "radiusSD" : 0,
    "name" : "Everton Park Hotel",
    "secondsFromGMT" : 36000,
    "lastSaved" : "2025-12-21T15:53:45Z",
    "longitude" : 152.9958252250345,
    "visitCount" : 1,
    "lastVisitDate" : "2014-07-06T02:26:40Z",
    "isStale" : false,
    "source" : "LocoKit",
    "foursquarePlaceId" : "4b6e21c7f964a520beac2ce3",
    "id" : "61CEACED-FFB8-4AE1-8BD9-C54B28878717"
  },
  {
    "countryCode" : "au",
    "latitude" : -27.503613,
    "rtreeId" : 941,
    "radiusMean" : 8,
    "streetAddress" : "Westfield Carindale",
    "visitDays" : 1,
    "radiusSD" : 0,
    "name" : "Origin Kebabs",
    "secondsFromGMT" : 36000,
    "locality" : "Carindale",
    "lastSaved" : "2025-12-26T20:48:20Z",
    "longitude" : 153.10200099999997,
    "visitCount" : 1,
    "lastVisitDate" : "2014-10-31T02:36:26Z",
    "isStale" : false,
    "source" : "LocoKit",
    "foursquarePlaceId" : "4bbd978af57ba593f43caeb9",
    "id" : "652987C8-2623-4129-9F78-4BCE9B374EDA"
  },
  {
    "rtreeId" : 962,
    "latitude" : -26.683084305700863,
    "radiusMean" : 8,
    "streetAddress" : "Sea Life Sunshine Coast Aquarium",
    "visitDays" : 1,
    "radiusSD" : 0,
    "name" : "Underwater World",
    "secondsFromGMT" : 36000,
    "lastSaved" : "2025-12-21T15:53:55Z",
    "longitude" : 153.121909426215,
    "visitCount" : 1,
    "lastVisitDate" : "2015-04-11T02:15:19Z",
    "isStale" : false,
    "source" : "LocoKit",
    "foursquarePlaceId" : "4d1143c999b78cfa88a1c8d5",
    "id" : "683965D4-236E-49DE-87B2-DAB32EE0180B"
  },
  {
    "countryCode" : "au",
    "latitude" : -27.55063578486443,
    "rtreeId" : 1015,
    "radiusMean" : 8,
    "streetAddress" : "557 Mount Gravatt-Capalaba Rd",
    "visitDays" : 1,
    "radiusSD" : 0,
    "name" : "Matilda Group",
    "secondsFromGMT" : 36000,
    "locality" : "Wishart",
    "lastSaved" : "2025-12-21T15:54:10Z",
    "longitude" : 153.1063321698457,
    "visitCount" : 1,
    "lastVisitDate" : "2018-05-03T10:20:52Z",
    "isStale" : false,
    "source" : "LocoKit",
    "foursquarePlaceId" : "5083adace4b0e5cc9b73c57d",
    "id" : "66B6E889-94F4-49C8-8337-B4F508B30744"
  },
  {
    "countryCode" : "au",
    "latitude" : -27.512398298469122,
    "rtreeId" : 1027,
    "radiusMean" : 12.306493206579248,
    "streetAddress" : "Greenslopes Private Hospital",
    "visitDays" : 2,
    "radiusSD" : 13.005176672810292,
    "name" : "Emergency Department, GPH",
    "secondsFromGMT" : 36000,
    "locality" : "Greenslopes",
    "lastSaved" : "2025-12-26T20:48:28Z",
    "longitude" : 153.04732236536066,
    "visitCount" : 2,
    "lastVisitDate" : "2020-10-16T04:07:35Z",
    "isStale" : false,
    "source" : "LocoKit",
    "id" : "604DF56A-E55C-404A-958C-031548020B03"
  },
  {
    "rtreeId" : 1051,
    "latitude" : -27.610506576402305,
    "radiusMean" : 10.916259889424007,
    "streetAddress" : "3263 Logan Rd",
    "visitDays" : 6,
    "radiusSD" : 8.477601971725207,
    "name" : "Jaycar Electronics",
    "secondsFromGMT" : 36000,
    "lastSaved" : "2025-12-21T15:54:20Z",
    "longitude" : 153.1140607075699,
    "visitCount" : 6,
    "lastVisitDate" : "2025-06-28T03:23:01Z",
    "isStale" : false,
    "source" : "LocoKit",
    "foursquarePlaceId" : "4c9d8153ca44236a09e52199",
    "id" : "63FC4D41-221C-446B-B125-2606B8B9D66A"
  },
  {
    "countryCode" : "au",
    "latitude" : -27.478008329795767,
    "rtreeId" : 1090,
    "radiusMean" : 8,
    "streetAddress" : "153 Little Stanley St",
    "visitDays" : 1,
    "radiusSD" : 1.1827124709735812,
    "name" : "Clem Jones Promenade",
    "secondsFromGMT" : 36000,
    "locality" : "South Brisbane",
    "lastSaved" : "2025-12-26T20:44:45Z",
    "longitude" : 153.02296778731207,
    "visitCount" : 1,
    "lastVisitDate" : "2018-12-22T10:02:09Z",
    "isStale" : false,
    "source" : "LocoKit",
    "foursquarePlaceId" : "4da3cbf822a5f04db6322c55",
    "id" : "676B2406-C146-40A7-BD4E-0753DAC22A0C"
  },
  {
    "countryCode" : "au",
    "latitude" : -27.503658092836,
    "rtreeId" : 1154,
    "radiusMean" : 8,
    "streetAddress" : "Westfield Carindale",
    "visitDays" : 1,
    "radiusSD" : 0,
    "name" : "Event Cinemas Carindale - Gold Class",
    "secondsFromGMT" : 36000,
    "locality" : "Carindale",
    "lastSaved" : "2025-12-26T20:48:19Z",
    "longitude" : 153.10201981895,
    "visitCount" : 1,
    "lastVisitDate" : "2016-07-04T01:12:29Z",
    "isStale" : false,
    "source" : "LocoKit",
    "id" : "656A8DC0-9D10-4BDF-9787-9D345C82FD57"
  },
  {
    "secondsFromGMT" : 36000,
    "latitude" : -27.48008871625475,
    "lastSaved" : "2025-12-26T20:45:53Z",
    "radiusSD" : 2.5083747540657564,
    "name" : "Epicurious",
    "rtreeId" : 1171,
    "foursquarePlaceId" : "53f921fb498e7a6931e11515",
    "visitCount" : 1,
    "longitude" : 153.0247753677517,
    "lastVisitDate" : "2018-07-18T02:20:32Z",
    "locality" : "South Brisbane",
    "isStale" : false,
    "id" : "6017D370-E168-4293-8856-2C5C0AD235CF",
    "streetAddress" : "445A Stanley St",
    "visitDays" : 1,
    "source" : "LocoKit",
    "radiusMean" : 8,
    "countryCode" : "au"
  },
  {
    "lastSaved" : "2025-12-21T15:54:46Z",
    "rtreeId" : 1173,
    "latitude" : -34.48331999999999,
    "radiusSD" : 0,
    "visitCount" : 1,
    "name" : "Maggie Beer's Farm Shop",
    "longitude" : 138.97674000000004,
    "lastVisitDate" : "2016-10-23T00:52:24Z",
    "isStale" : false,
    "id" : "69F6A4F1-D362-49DF-BCAB-08D7C0D92D6E",
    "visitDays" : 1,
    "source" : "LocoKit",
    "radiusMean" : 8
  },
  {
    "lastSaved" : "2025-12-21T15:54:48Z",
    "rtreeId" : 1180,
    "latitude" : -26.630942932373205,
    "radiusSD" : 0,
    "visitCount" : 1,
    "name" : "Twin Waters River Jetty",
    "longitude" : 153.101251972603,
    "lastVisitDate" : "2018-01-03T08:22:03Z",
    "isStale" : false,
    "id" : "6C05F16F-61D0-4A62-B233-45C8DC9171C6",
    "visitDays" : 1,
    "source" : "LocoKit",
    "radiusMean" : 8
  },
  {
    "secondsFromGMT" : 36000,
    "latitude" : -27.502207000000002,
    "lastSaved" : "2025-12-26T20:44:42Z",
    "radiusSD" : 0,
    "name" : "CODA",
    "rtreeId" : 1201,
    "foursquarePlaceId" : "4f59496fe4b04edd0b4e1aec",
    "visitCount" : 1,
    "longitude" : 153.04093,
    "lastVisitDate" : "2017-10-06T23:21:42Z",
    "locality" : "Greenslopes",
    "isStale" : false,
    "id" : "6920CCC6-3B78-4637-B28E-A7D9DA68F03B",
    "streetAddress" : "1 Earl St",
    "visitDays" : 1,
    "source" : "LocoKit",
    "radiusMean" : 8,
    "countryCode" : "au"
  },
  {
    "secondsFromGMT" : 36000,
    "latitude" : -28.028285608493,
    "lastSaved" : "2025-12-30T13:24:17Z",
    "radiusSD" : 0,
    "name" : "Gold Coast Convention and Exhibition Centre",
    "rtreeId" : 1214,
    "visitCount" : 1,
    "longitude" : 153.42929978104,
    "lastVisitDate" : "2017-02-05T00:59:07Z",
    "locality" : "Broadbeach",
    "isStale" : false,
    "id" : "6ADE313C-65A8-412A-B7F5-B04178FDA6BB",
    "streetAddress" : "Gold Coast Convention and Exhibition Centre",
    "visitDays" : 1,
    "source" : "LocoKit",
    "radiusMean" : 8,
    "countryCode" : "au"
  },
  {
    "secondsFromGMT" : 36000,
    "rtreeId" : 1215,
    "latitude" : -27.454384188750577,
    "radiusSD" : 57.35973628218714,
    "lastSaved" : "2025-12-21T15:54:54Z",
    "name" : "Edwards Scientific",
    "visitCount" : 2,
    "longitude" : 153.10430203401475,
    "lastVisitDate" : "2025-09-27T06:36:33Z",
    "isStale" : false,
    "id" : "6E25B339-1761-4540-A9D5-755DCB5456CE",
    "streetAddress" : "49 Borthwick Ave",
    "visitDays" : 2,
    "source" : "LocoKit",
    "radiusMean" : 52.458025366071695
  },
  {
    "lastSaved" : "2025-12-21T15:54:57Z",
    "rtreeId" : 1231,
    "latitude" : -27.087030999999996,
    "radiusSD" : 0,
    "visitCount" : 1,
    "name" : "Bribie Island Seaside Museum",
    "foursquarePlaceId" : "502f0fc1e4b021f7a4d98486",
    "longitude" : 153.15899999999996,
    "lastVisitDate" : "2016-11-19T05:04:48Z",
    "isStale" : false,
    "id" : "689ED049-6046-41BF-8292-C7B34B72ADDD",
    "visitDays" : 1,
    "source" : "LocoKit",
    "radiusMean" : 8
  },
  {
    "lastSaved" : "2025-12-21T15:54:59Z",
    "rtreeId" : 1241,
    "latitude" : -27.06914261746652,
    "radiusSD" : 4.945336976993098,
    "visitCount" : 2,
    "name" : "Woorim Beach",
    "foursquarePlaceId" : "4bb94ce5935e9521660c2790",
    "longitude" : 153.20399599030338,
    "lastVisitDate" : "2022-09-22T05:11:53Z",
    "isStale" : false,
    "id" : "67EBF6A3-A26D-49C5-A0B0-B6B6F33941BD",
    "visitDays" : 2,
    "source" : "LocoKit",
    "radiusMean" : 23.257557344471422
  },
  {
    "radiusSD" : 0,
    "radiusMean" : 8,
    "isStale" : false,
    "source" : "LocoKit",
    "lastSaved" : "2025-12-21T15:55:07Z",
    "name" : "Star Track Express Darra",
    "visitCount" : 1,
    "longitude" : 152.94383199352,
    "visitDays" : 1,
    "rtreeId" : 1275,
    "lastVisitDate" : "2017-11-17T03:26:57Z",
    "latitude" : -27.56534912540001,
    "id" : "69A2F236-7107-4A10-A5F7-3848C8B22E8F"
  },
  {
    "lastVisitDate" : "2018-01-06T05:32:11Z",
    "radiusSD" : 0,
    "radiusMean" : 8,
    "isStale" : false,
    "source" : "LocoKit",
    "lastSaved" : "2025-12-21T15:55:08Z",
    "name" : "Mountain View Cafe",
    "visitCount" : 1,
    "longitude" : 152.8804,
    "visitDays" : 1,
    "rtreeId" : 1280,
    "foursquarePlaceId" : "5a51a8e1d1a402679217ddbd",
    "latitude" : -26.780892,
    "id" : "664C10D1-E162-463C-AFCC-08180B0FB7EA"
  },
  {
    "radiusSD" : 0,
    "radiusMean" : 8,
    "isStale" : false,
    "source" : "LocoKit",
    "lastSaved" : "2025-12-21T15:55:10Z",
    "name" : "Glass house",
    "visitCount" : 1,
    "longitude" : 153.12425266120476,
    "visitDays" : 1,
    "rtreeId" : 1285,
    "lastVisitDate" : "2016-01-06T05:19:25Z",
    "latitude" : -30.293617441174373,
    "id" : "6B965A5C-12F6-4829-8F91-3E44A9F6E07C"
  },
  {
    "lastVisitDate" : "2016-12-26T02:35:07Z",
    "radiusSD" : 0.011151604150471898,
    "radiusMean" : 8,
    "streetAddress" : "Westfield Mt Gravatt",
    "isStale" : false,
    "locality" : "Upper Mount Gravatt",
    "source" : "LocoKit",
    "lastSaved" : "2025-12-21T15:55:13Z",
    "secondsFromGMT" : 36000,
    "name" : "Hanachi Garden City",
    "visitCount" : 1,
    "longitude" : 153.0808702,
    "visitDays" : 1,
    "countryCode" : "au",
    "rtreeId" : 1306,
    "latitude" : -27.562372075757263,
    "id" : "6D189089-276F-449F-B4CF-34D322FF264E"
  },
  {
    "radiusSD" : 0,
    "radiusMean" : 8,
    "isStale" : false,
    "source" : "LocoKit",
    "lastSaved" : "2025-12-21T15:55:20Z",
    "name" : "Whistler Wines",
    "visitCount" : 1,
    "longitude" : 138.95590280958,
    "visitDays" : 1,
    "rtreeId" : 1346,
    "lastVisitDate" : "2016-10-23T01:53:36Z",
    "latitude" : -34.491303634225,
    "id" : "614C019D-4075-4341-A953-447BE314EE9B"
  },
  {
    "lastVisitDate" : "2017-06-17T05:54:00Z",
    "radiusSD" : 0,
    "radiusMean" : 8,
    "isStale" : false,
    "source" : "LocoKit",
    "lastSaved" : "2025-12-21T15:55:21Z",
    "name" : "Kidstuff",
    "visitCount" : 1,
    "longitude" : 153.03388,
    "visitDays" : 1,
    "rtreeId" : 1357,
    "foursquarePlaceId" : "58086a3838fa47c09f408467",
    "latitude" : -27.382132000000006,
    "id" : "6809F9FE-94C1-4778-95D6-5239381CD431"
  },
  {
    "foursquarePlaceId" : "4bef9a8eb0b376b0dde1dab3",
    "radiusSD" : 14.514788329684238,
    "radiusMean" : 30.411613968563028,
    "lastVisitDate" : "2021-07-11T07:02:40Z",
    "streetAddress" : "77 Lower River Tce",
    "isStale" : false,
    "locality" : "Kangaroo Point",
    "source" : "LocoKit",
    "lastSaved" : "2025-12-26T20:42:26Z",
    "secondsFromGMT" : 36000,
    "name" : "Maritime Museum Ferry Terminal",
    "visitCount" : 3,
    "longitude" : 153.0288666994814,
    "visitDays" : 3,
    "countryCode" : "au",
    "rtreeId" : 1358,
    "latitude" : -27.482190974395042,
    "id" : "60F0A6A2-599C-45C4-B8EF-FCCDEF5C82F5"
  },
  {
    "countryCode" : "au",
    "rtreeId" : 1374,
    "streetAddress" : "44A Ferry St",
    "isStale" : false,
    "radiusMean" : 8,
    "visitCount" : 1,
    "visitDays" : 1,
    "source" : "LocoKit",
    "secondsFromGMT" : 36000,
    "lastVisitDate" : "2017-03-25T07:38:15Z",
    "locality" : "Kangaroo Point",
    "longitude" : 153.03886000000003,
    "radiusSD" : 0,
    "latitude" : -27.471664000000004,
    "lastSaved" : "2025-12-26T20:47:07Z",
    "id" : "61737EA4-286D-417A-8AB9-AD24C53E2D3A",
    "name" : "The Landing at Dockside",
    "foursquarePlaceId" : "4c74cea3d8948cfaed0166da"
  },
  {
    "rtreeId" : 1377,
    "isStale" : false,
    "streetAddress" : "O'Reilly's Rainforest Retreat",
    "radiusMean" : 8,
    "visitCount" : 1,
    "visitDays" : 1,
    "source" : "LocoKit",
    "secondsFromGMT" : 36000,
    "lastVisitDate" : "2020-09-20T21:25:22Z",
    "longitude" : 153.13471646163214,
    "radiusSD" : 1.4505904177303917,
    "latitude" : -28.23033092245711,
    "lastSaved" : "2025-12-21T15:55:25Z",
    "id" : "6C2D0838-118A-4EED-8156-56F81FCF99BA",
    "name" : "Stinson Crash Memorial"
  },
  {
    "rtreeId" : 1383,
    "isStale" : false,
    "streetAddress" : "West Canungra Creek Cct",
    "radiusMean" : 46.57256415383296,
    "visitCount" : 2,
    "visitDays" : 1,
    "source" : "LocoKit",
    "secondsFromGMT" : 36000,
    "lastVisitDate" : "2020-09-25T03:34:12Z",
    "longitude" : 153.1541059262496,
    "radiusSD" : 8.588520214623554,
    "latitude" : -28.241542136695163,
    "lastSaved" : "2025-12-21T15:55:26Z",
    "id" : "6EC232F1-C581-473E-84C9-4BC6F902A9D5",
    "name" : "Box log falls"
  },
  {
    "countryCode" : "au",
    "rtreeId" : 1391,
    "streetAddress" : "41 Aspire St",
    "isStale" : false,
    "radiusMean" : 8,
    "visitCount" : 1,
    "visitDays" : 1,
    "source" : "LocoKit",
    "secondsFromGMT" : 36000,
    "lastVisitDate" : "2020-10-05T04:27:20Z",
    "locality" : "Rochedale",
    "longitude" : 153.12054694187887,
    "radiusSD" : 2.8649536638008093,
    "latitude" : -27.575063868465403,
    "lastSaved" : "2025-12-21T20:21:11Z",
    "id" : "68559BD0-A4A4-4A32-9C94-5A7CAA6667D3",
    "name" : "Central Park"
  },
  {
    "rtreeId" : 1424,
    "isStale" : false,
    "radiusMean" : 8,
    "visitCount" : 1,
    "visitDays" : 1,
    "source" : "LocoKit",
    "lastVisitDate" : "2021-01-06T01:37:27Z",
    "longitude" : 153.2670721439557,
    "radiusSD" : 2.0293382541952267,
    "latitude" : -28.187622819247718,
    "lastSaved" : "2025-12-21T15:55:32Z",
    "id" : "606A8C3D-2ED7-4BE4-9F95-AF38C1278B85",
    "name" : "Tanninaba Falls"
  },
  {
    "rtreeId" : 1443,
    "isStale" : false,
    "radiusMean" : 8,
    "visitCount" : 1,
    "visitDays" : 1,
    "source" : "LocoKit",
    "lastVisitDate" : "2021-01-23T08:43:12Z",
    "longitude" : 153.06069096528302,
    "radiusSD" : 1.4485844735252091,
    "latitude" : -27.44003091982498,
    "lastSaved" : "2025-12-21T15:55:35Z",
    "id" : "65DBACD8-A9C7-4C36-9C86-BB5F0D0BD0BE",
    "name" : "Lores Bonney Riverwalk"
  },
  {
    "rtreeId" : 1460,
    "isStale" : false,
    "radiusMean" : 8,
    "visitCount" : 1,
    "visitDays" : 1,
    "source" : "LocoKit",
    "lastVisitDate" : "2021-02-20T03:49:20Z",
    "longitude" : 153.0964124407907,
    "radiusSD" : 5.308429289198279,
    "latitude" : -27.473254416774086,
    "lastSaved" : "2025-12-21T15:55:38Z",
    "id" : "6A0F271B-72F6-4909-A4F8-AA84B754C6A3",
    "name" : "Bunnings - Camp Hill"
  },
  {
    "lastVisitDate" : "2021-07-06T03:40:13Z",
    "longitude" : 151.91746369122677,
    "isStale" : false,
    "latitude" : -28.84527780931347,
    "visitDays" : 1,
    "id" : "6CE6455C-F8D6-44FA-ADF6-8E68C6441CBA",
    "streetAddress" : "Wyberba",
    "secondsFromGMT" : 36000,
    "radiusMean" : 29.076242456239438,
    "rtreeId" : 1499,
    "name" : "Echidna rock",
    "source" : "LocoKit",
    "radiusSD" : 12.946206952390792,
    "lastSaved" : "2025-12-21T15:55:45Z",
    "visitCount" : 2
  },
  {
    "lastVisitDate" : "2021-07-07T00:24:47Z",
    "longitude" : 151.93732395146984,
    "isStale" : false,
    "latitude" : -28.827334751821763,
    "visitDays" : 1,
    "id" : "6CC49615-9ACB-4A47-9BCA-D316E56F2634",
    "streetAddress" : "Girraween National Park",
    "secondsFromGMT" : 36000,
    "radiusMean" : 8,
    "rtreeId" : 1506,
    "name" : "Granite Arch",
    "source" : "LocoKit",
    "radiusSD" : 3.2541750541862995,
    "lastSaved" : "2025-12-21T15:55:46Z",
    "visitCount" : 1
  },
  {
    "lastVisitDate" : "2023-01-06T01:28:41Z",
    "longitude" : 153.0346953521817,
    "latitude" : -27.502005017205388,
    "isStale" : false,
    "foursquarePlaceId" : "4be9f643a9900f4787051640",
    "visitDays" : 2,
    "id" : "63CDEAFB-FDC9-4FF6-A76E-3EDB4D5E0B5A",
    "locality" : "Annerley",
    "streetAddress" : "310 Ipswich Rd",
    "secondsFromGMT" : 36000,
    "radiusMean" : 15.974457922151757,
    "countryCode" : "au",
    "rtreeId" : 1529,
    "name" : "Qscan",
    "source" : "LocoKit",
    "radiusSD" : 6.314939222021725,
    "lastSaved" : "2025-12-26T20:43:39Z",
    "visitCount" : 2
  },
  {
    "lastVisitDate" : "2021-11-26T21:29:06Z",
    "longitude" : 153.09207419452682,
    "latitude" : -27.546663731859095,
    "isStale" : false,
    "foursquarePlaceId" : "5d6c54d7d3702c0008f465e9",
    "visitDays" : 3,
    "id" : "660D3B3E-6050-4643-8079-9CCF6285D657",
    "locality" : "Upper Mount Gravatt",
    "streetAddress" : "196 Wishart Rd",
    "secondsFromGMT" : 36000,
    "radiusMean" : 8,
    "countryCode" : "au",
    "rtreeId" : 1530,
    "name" : "The Gift Shop Food & Drink",
    "source" : "LocoKit",
    "radiusSD" : 4.435397165165692,
    "lastSaved" : "2025-12-21T15:55:50Z",
    "visitCount" : 3
  },
  {
    "lastVisitDate" : "2025-10-31T21:39:51Z",
    "longitude" : 153.07833424110333,
    "isStale" : false,
    "latitude" : -27.505855859234682,
    "visitDays" : 2,
    "id" : "672712A4-FE78-4FC1-A70B-F94C949E8438",
    "streetAddress" : "Whites Hill Reserve",
    "secondsFromGMT" : 36000,
    "radiusMean" : 14.79674808152682,
    "rtreeId" : 1541,
    "name" : "Whites Hill Summit",
    "source" : "LocoKit",
    "radiusSD" : 11.614344202309063,
    "lastSaved" : "2025-12-21T15:55:52Z",
    "visitCount" : 3
  },
  {
    "lastVisitDate" : "2016-10-19T01:12:34Z",
    "longitude" : 138.5379504761904,
    "latitude" : -34.939391571428594,
    "isStale" : false,
    "foursquarePlaceId" : "4d8ecc1cd265236afe891317",
    "visitDays" : 1,
    "id" : "675C7A93-9F1D-46AB-BC32-F9E69DD43CA0",
    "radiusMean" : 8,
    "rtreeId" : 1569,
    "name" : "Gate 20",
    "source" : "LocoKit",
    "radiusSD" : 0.8434037317645126,
    "lastSaved" : "2025-12-21T15:55:57Z",
    "visitCount" : 1
  },
  {
    "lastVisitDate" : "2021-12-17T08:30:23Z",
    "longitude" : 153.1812354360811,
    "latitude" : -27.950560215153168,
    "isStale" : false,
    "visitDays" : 1,
    "id" : "6F0AA64E-7C7E-4917-80E2-0270AD78A9EF",
    "radiusMean" : 14.777041417058106,
    "rtreeId" : 1595,
    "name" : "Hang Gliders Launch",
    "source" : "LocoKit",
    "radiusSD" : 3.311896012906215,
    "lastSaved" : "2025-12-21T15:56:02Z",
    "visitCount" : 1
  },
  {
    "lastVisitDate" : "2021-12-17T07:14:53Z",
    "longitude" : 153.19826225400777,
    "latitude" : -27.972407187931143,
    "isStale" : false,
    "visitDays" : 2,
    "id" : "6314293A-BE54-4D14-A30D-FC36A568D702",
    "radiusMean" : 11.159229593987776,
    "rtreeId" : 1599,
    "name" : "Gabby’s Cafe",
    "source" : "LocoKit",
    "radiusSD" : 5.787258044194971,
    "lastSaved" : "2025-12-21T15:56:02Z",
    "visitCount" : 3
  },
  {
    "lastVisitDate" : "2022-01-23T04:59:05Z",
    "longitude" : 153.08360560801836,
    "latitude" : -27.563208004161304,
    "isStale" : false,
    "visitDays" : 1,
    "id" : "62CB6EE4-B533-4EF6-9466-289F7E998969",
    "locality" : "Upper Mount Gravatt",
    "streetAddress" : "Westfield Mt Gravatt",
    "secondsFromGMT" : 36000,
    "radiusMean" : 8,
    "countryCode" : "au",
    "rtreeId" : 1610,
    "name" : "Adairs",
    "source" : "LocoKit",
    "radiusSD" : 3.4220394376598513,
    "lastSaved" : "2025-12-21T15:56:04Z",
    "visitCount" : 1
  },
  {
    "latitude" : -27.57150180860835,
    "id" : "698EC313-8F7B-4F9D-9EA7-7D7B995B393E",
    "locality" : "Sunnybank",
    "longitude" : 153.06282992202543,
    "radiusSD" : 3.6240080438895874,
    "countryCode" : "au",
    "streetAddress" : "314–326 McCullough St",
    "radiusMean" : 8,
    "lastSaved" : "2025-12-21T15:56:09Z",
    "secondsFromGMT" : 36000,
    "isStale" : false,
    "rtreeId" : 1638,
    "name" : "E’Langa EV Chargers",
    "visitDays" : 6,
    "lastVisitDate" : "2022-05-08T02:57:07Z",
    "source" : "LocoKit",
    "visitCount" : 6
  },
  {
    "latitude" : -27.198701418997434,
    "id" : "6A75B2C4-089F-4231-9A71-AD9291C88069",
    "longitude" : 153.11550072793813,
    "radiusSD" : 18.908781695735513,
    "radiusMean" : 20.519772585301745,
    "lastSaved" : "2025-12-21T15:56:11Z",
    "rtreeId" : 1650,
    "isStale" : false,
    "name" : "Marvelous Fish & Chips",
    "visitDays" : 1,
    "lastVisitDate" : "2022-08-20T06:44:21Z",
    "source" : "LocoKit",
    "visitCount" : 1
  },
  {
    "latitude" : -26.214697917336544,
    "id" : "69AAC014-CD4C-46C6-868A-A80C0B4EECC3",
    "longitude" : 152.68332431029282,
    "radiusSD" : 20.912080311907772,
    "radiusMean" : 12.37041671632199,
    "foursquarePlaceId" : "4e81324f61affaf91fddb785",
    "lastSaved" : "2025-12-21T15:56:17Z",
    "rtreeId" : 1680,
    "isStale" : false,
    "name" : "Lake Alford Recreation Area",
    "visitDays" : 1,
    "lastVisitDate" : "2022-10-01T02:21:26Z",
    "source" : "LocoKit",
    "visitCount" : 1
  },
  {
    "latitude" : -26.918024413603078,
    "id" : "6E8AF009-7489-49EA-A8F6-1A56CDE9941D",
    "longitude" : 152.99625866746575,
    "radiusSD" : 11.375629917870079,
    "streetAddress" : "Coochin Creek",
    "radiusMean" : 21.625270429521454,
    "foursquarePlaceId" : "52a1ed2a498edb441f05d641",
    "lastSaved" : "2025-12-21T15:56:17Z",
    "secondsFromGMT" : 36000,
    "isStale" : false,
    "rtreeId" : 1681,
    "name" : "McDonald's",
    "visitDays" : 4,
    "lastVisitDate" : "2025-08-09T08:38:35Z",
    "source" : "LocoKit",
    "visitCount" : 4
  },
  {
    "latitude" : -27.56778719900511,
    "id" : "652AAF97-AB4D-4F64-A74E-6373B0FBAC69",
    "locality" : "Eight Mile Plains",
    "longitude" : 153.100040321861,
    "radiusSD" : 7.459424263820871,
    "countryCode" : "au",
    "streetAddress" : "Malinya Place Park",
    "radiusMean" : 15.7693337033386,
    "lastSaved" : "2025-12-21T15:56:34Z",
    "secondsFromGMT" : 36000,
    "isStale" : false,
    "rtreeId" : 1780,
    "name" : "Nardie Street Park",
    "visitDays" : 6,
    "lastVisitDate" : "2023-09-02T21:35:26Z",
    "source" : "LocoKit",
    "visitCount" : 6
  },
  {
    "latitude" : -27.365885331673578,
    "id" : "6BE33F0A-CCB3-447E-8F4A-1222749EBDA0",
    "longitude" : 152.17979804467586,
    "radiusSD" : 1.7640366519598114,
    "radiusMean" : 8,
    "foursquarePlaceId" : "5ee420970aebd90007c1ea23",
    "lastSaved" : "2025-12-21T15:56:36Z",
    "rtreeId" : 1785,
    "isStale" : false,
    "name" : "Ravensbourne National Park",
    "visitDays" : 1,
    "lastVisitDate" : "2022-12-26T07:08:20Z",
    "source" : "LocoKit",
    "visitCount" : 1
  },
  {
    "latitude" : -27.49188180938055,
    "id" : "62B58BE2-7DC2-4BD0-A4B6-11C4AF4364E1",
    "longitude" : 153.2177396240602,
    "radiusSD" : 2.461810930007576,
    "radiusMean" : 8,
    "foursquarePlaceId" : "5a26468ed552c759b7b01d66",
    "lastSaved" : "2025-12-21T15:56:39Z",
    "rtreeId" : 1800,
    "isStale" : false,
    "name" : "Noodle Box",
    "visitDays" : 1,
    "lastVisitDate" : "2023-01-07T08:14:22Z",
    "source" : "LocoKit",
    "visitCount" : 1
  },
  {
    "latitude" : -28.02949046072277,
    "id" : "6DA476CF-52BA-4216-B936-A9BC95964471",
    "locality" : "Broadbeach",
    "longitude" : 153.43459309725841,
    "radiusSD" : 5.3602331288687175,
    "countryCode" : "au",
    "streetAddress" : "Robert Gatenby Boardwalk",
    "radiusMean" : 8,
    "foursquarePlaceId" : "4b43a0a3f964a520abe425e3",
    "lastSaved" : "2025-12-30T13:24:20Z",
    "secondsFromGMT" : 36000,
    "isStale" : false,
    "rtreeId" : 1806,
    "name" : "Kurrawa Beach",
    "visitDays" : 1,
    "lastVisitDate" : "2023-01-15T08:44:54Z",
    "source" : "LocoKit",
    "visitCount" : 1
  },
  {
    "latitude" : -27.93712703251522,
    "id" : "6054903B-E600-4658-AC5D-28C4E725DF7F",
    "longitude" : 153.42571297207323,
    "radiusSD" : 2.2317585359546155,
    "radiusMean" : 8,
    "foursquarePlaceId" : "4b49886df964a520fa7026e3",
    "lastSaved" : "2025-12-21T15:56:40Z",
    "rtreeId" : 1808,
    "isStale" : false,
    "name" : "Gold Coast Seaway",
    "visitDays" : 1,
    "lastVisitDate" : "2023-01-14T06:44:12Z",
    "source" : "LocoKit",
    "visitCount" : 1
  },
  {
    "name" : "Yowie Park",
    "visitCount" : 1,
    "longitude" : 152.5645720289677,
    "lastSaved" : "2025-12-21T15:56:42Z",
    "radiusMean" : 8,
    "id" : "622B7E69-14CC-440B-A38A-8B93F205494A",
    "foursquarePlaceId" : "61c57a4e2a8879689e7e2673",
    "visitDays" : 1,
    "rtreeId" : 1819,
    "source" : "LocoKit",
    "radiusSD" : 1.0246467964173906,
    "latitude" : -26.947673952275753,
    "isStale" : false,
    "lastVisitDate" : "2023-01-26T04:07:47Z"
  },
  {
    "name" : "Mount Mee Lookout",
    "visitCount" : 1,
    "longitude" : 152.78103417178508,
    "lastSaved" : "2025-12-21T15:56:43Z",
    "radiusMean" : 8,
    "id" : "6E0F7369-3464-41FB-98BD-A4ACD21C9B9F",
    "foursquarePlaceId" : "4bb42f29737d76b013393b7c",
    "visitDays" : 1,
    "rtreeId" : 1825,
    "source" : "LocoKit",
    "radiusSD" : 0.8783709399855094,
    "latitude" : -27.065737182292352,
    "isStale" : false,
    "lastVisitDate" : "2023-02-05T07:23:00Z"
  },
  {
    "name" : "Gate 4",
    "visitCount" : 2,
    "longitude" : 144.84988351768612,
    "lastSaved" : "2025-12-21T15:56:48Z",
    "radiusMean" : 28.297948379876477,
    "id" : "69EB01DD-75B2-4B5B-8FED-E4332492EEBC",
    "foursquarePlaceId" : "4c888151944e224bc5071d85",
    "visitDays" : 1,
    "rtreeId" : 1850,
    "source" : "LocoKit",
    "radiusSD" : 18.386364764808576,
    "latitude" : -37.66731665638617,
    "isStale" : false,
    "lastVisitDate" : "2023-02-19T06:16:06Z"
  },
  {
    "source" : "LocoKit",
    "locality" : "Yandina",
    "visitCount" : 3,
    "name" : "Gun Cotton Coffee Roasters",
    "streetAddress" : "13A Railway St",
    "id" : "6C827B92-9CC4-40B0-9735-990A1752AA3B",
    "lastSaved" : "2026-01-02T02:58:33Z",
    "longitude" : 152.9574127985425,
    "isStale" : false,
    "rtreeId" : 1865,
    "lastVisitDate" : "2024-04-27T01:10:41Z",
    "foursquarePlaceId" : "63a8f9f6c459fd5a98620d12",
    "countryCode" : "au",
    "radiusMean" : 8,
    "latitude" : -26.560507065708375,
    "visitDays" : 3,
    "radiusSD" : 17.789932335561573,
    "secondsFromGMT" : 36000
  },
  {
    "source" : "LocoKit",
    "visitCount" : 3,
    "name" : "Sealife Sydney Aquarium",
    "id" : "64EBEF5F-B572-42E7-84A7-4443320244D1",
    "rtreeId" : 1882,
    "lastSaved" : "2025-12-21T15:56:54Z",
    "isStale" : false,
    "longitude" : 151.20194364363275,
    "lastVisitDate" : "2023-03-12T03:45:46Z",
    "foursquarePlaceId" : "4b058761f964a520198f22e3",
    "radiusMean" : 25.592300134275035,
    "latitude" : -33.86968796189434,
    "visitDays" : 1,
    "radiusSD" : 22.29653503121424
  },
  {
    "source" : "LocoKit",
    "visitCount" : 2,
    "name" : "Baywatch Cafe",
    "id" : "614FD530-82B4-4515-B19A-614ACF8974F7",
    "rtreeId" : 1888,
    "lastSaved" : "2025-12-21T15:56:55Z",
    "isStale" : false,
    "longitude" : 153.18637921039178,
    "lastVisitDate" : "2023-03-18T08:36:57Z",
    "foursquarePlaceId" : "4b11ef38f964a520308723e3",
    "radiusMean" : 8,
    "latitude" : -27.45205144707585,
    "visitDays" : 2,
    "radiusSD" : 2.525294701045041
  },
  {
    "source" : "LocoKit",
    "visitCount" : 1,
    "name" : "Rocks Riverside Park",
    "id" : "62E559A4-F62E-44E8-85E7-3522F44E0FA9",
    "rtreeId" : 1903,
    "lastSaved" : "2025-12-21T15:56:57Z",
    "isStale" : false,
    "longitude" : 152.95970812110946,
    "lastVisitDate" : "2023-04-08T07:16:20Z",
    "foursquarePlaceId" : "4b5e773cf964a520da8f29e3",
    "radiusMean" : 8,
    "latitude" : -27.541089706084826,
    "visitDays" : 1,
    "radiusSD" : 2.247591924154309
  },
  {
    "source" : "LocoKit",
    "locality" : "South Brisbane",
    "visitCount" : 1,
    "name" : "Griffith Business School",
    "streetAddress" : "Griffith University",
    "id" : "666CC1EE-F6F5-406C-A110-96777D384694",
    "lastSaved" : "2025-12-26T20:45:55Z",
    "longitude" : 153.02434036583634,
    "isStale" : false,
    "rtreeId" : 1907,
    "lastVisitDate" : "2023-04-11T06:42:20Z",
    "foursquarePlaceId" : "4cb56babe262b60c4c7467e0",
    "countryCode" : "au",
    "radiusMean" : 8,
    "latitude" : -27.481829008161814,
    "visitDays" : 1,
    "radiusSD" : 4.832700174369673,
    "secondsFromGMT" : 36000
  },
  {
    "source" : "LocoKit",
    "locality" : "Bowen Hills",
    "visitCount" : 6,
    "name" : "John Reid Pavilion",
    "streetAddress" : "Brisbane Showgrounds",
    "id" : "6B1B15D0-4B00-4B5B-9782-99ABF73D5FA7",
    "lastSaved" : "2025-12-26T20:50:38Z",
    "longitude" : 153.03198105044962,
    "isStale" : false,
    "rtreeId" : 1943,
    "lastVisitDate" : "2024-06-16T01:25:36Z",
    "foursquarePlaceId" : "5faf9a4443f3f9770b7647dc",
    "countryCode" : "au",
    "radiusMean" : 80.62009601892538,
    "latitude" : -27.451302337634242,
    "visitDays" : 4,
    "radiusSD" : 17.108595451521385,
    "secondsFromGMT" : 36000
  },
  {
    "source" : "LocoKit",
    "locality" : "West End",
    "visitCount" : 1,
    "name" : "Senior Art, West End",
    "streetAddress" : "198 Montague Rd",
    "id" : "6A427672-5526-4C8C-BBF0-C354F985AA4B",
    "lastSaved" : "2025-12-26T20:44:41Z",
    "longitude" : 153.00924008659018,
    "isStale" : false,
    "rtreeId" : 1954,
    "lastVisitDate" : "2023-07-23T03:58:31Z",
    "countryCode" : "au",
    "radiusMean" : 8.854482500442709,
    "latitude" : -27.476336520691316,
    "visitDays" : 1,
    "radiusSD" : 8.636253798936655,
    "secondsFromGMT" : 36000
  },
  {
    "source" : "LocoKit",
    "visitCount" : 1,
    "name" : "The Grand Old Crow Hotel",
    "id" : "6F5081DC-2808-4FD5-8035-49FE914E27EA",
    "rtreeId" : 1981,
    "lastSaved" : "2025-12-21T15:57:07Z",
    "isStale" : false,
    "longitude" : 152.0547018439334,
    "lastVisitDate" : "2023-10-31T03:36:02Z",
    "radiusMean" : 11.724365642443573,
    "latitude" : -27.260628693739132,
    "visitDays" : 1,
    "radiusSD" : 5.401117733208262
  },
  {
    "source" : "LocoKit",
    "visitCount" : 7,
    "name" : "QESH EV Charger, Esk",
    "streetAddress" : "Lot 13 Highland St",
    "id" : "6691CA18-8184-4D82-884A-95B79B1ADD69",
    "isStale" : false,
    "rtreeId" : 1989,
    "lastSaved" : "2025-12-21T15:57:08Z",
    "longitude" : 152.42030569988447,
    "lastVisitDate" : "2025-10-04T02:09:59Z",
    "radiusMean" : 8,
    "latitude" : -27.239099794630185,
    "visitDays" : 4,
    "radiusSD" : 3.8462178502693964,
    "secondsFromGMT" : 36000
  },
  {
    "secondsFromGMT" : 36000,
    "countryCode" : "au",
    "source" : "LocoKit",
    "lastSaved" : "2025-12-24T05:19:23Z",
    "name" : "Mr Wong's Chinese Restaurant",
    "radiusMean" : 8,
    "streetAddress" : "64 Kedron Brook Rd",
    "mapboxPlaceId" : "poi.377957196856",
    "mapboxCategory" : "chinese restaurant, chinese food, restaurant",
    "rtreeId" : 2004,
    "longitude" : 153.0203638901078,
    "visitCount" : 2,
    "visitDays" : 1,
    "id" : "615D8814-24FA-4DC9-ADB0-F785900DF2E1",
    "isStale" : false,
    "locality" : "Wilston",
    "radiusSD" : 1.1160766372801698,
    "lastVisitDate" : "2023-11-09T23:59:43Z",
    "latitude" : -27.433287006540336
  },
  {
    "secondsFromGMT" : 36000,
    "countryCode" : "au",
    "source" : "LocoKit",
    "lastSaved" : "2025-12-23T21:57:35Z",
    "name" : "Andy’s Place",
    "radiusMean" : 8,
    "streetAddress" : "30 Dunedin St",
    "rtreeId" : 2014,
    "longitude" : 153.06405877446812,
    "visitCount" : 1,
    "visitDays" : 1,
    "id" : "6EE4A569-3C89-4FF2-A664-93CFF5799CC9",
    "isStale" : false,
    "locality" : "Sunnybank",
    "radiusSD" : 0.0036227423422002126,
    "lastVisitDate" : "2023-12-09T11:14:59Z",
    "latitude" : -27.58036770334841
  },
  {
    "secondsFromGMT" : 36000,
    "countryCode" : "au",
    "source" : "LocoKit",
    "lastSaved" : "2025-12-21T15:57:12Z",
    "name" : "Dominoes Pizza",
    "radiusMean" : 8,
    "streetAddress" : "Wishart Shopping Village",
    "rtreeId" : 2016,
    "longitude" : 153.10692864934217,
    "visitCount" : 1,
    "visitDays" : 1,
    "id" : "6D03D363-8DE0-44EB-BC4C-21B98FC2CE56",
    "isStale" : false,
    "locality" : "Wishart",
    "radiusSD" : 1.6196161844669343,
    "lastVisitDate" : "2023-12-11T09:25:51Z",
    "latitude" : -27.549022946782507
  },
  {
    "secondsFromGMT" : 36000,
    "source" : "LocoKit",
    "lastSaved" : "2025-12-21T15:57:21Z",
    "name" : "MCA Superstore ",
    "radiusMean" : 8,
    "streetAddress" : "76 Moss St",
    "rtreeId" : 2098,
    "longitude" : 153.12446030490094,
    "visitCount" : 1,
    "visitDays" : 1,
    "id" : "604BE417-2230-4578-A7E6-7FB81A1B01FD",
    "isStale" : false,
    "radiusSD" : 0.911177346333303,
    "lastVisitDate" : "2024-04-13T02:01:37Z",
    "latitude" : -27.620739634710375
  },
  {
    "secondsFromGMT" : 36000,
    "source" : "LocoKit",
    "lastSaved" : "2025-12-21T16:22:50Z",
    "name" : "Peregian Park",
    "radiusMean" : 22.796308353728374,
    "streetAddress" : "Heron St.",
    "mapboxPlaceId" : "poi.326417590980",
    "mapboxCategory" : "park, leisure",
    "rtreeId" : 2105,
    "longitude" : 153.0969104393896,
    "visitCount" : 2,
    "visitDays" : 1,
    "id" : "693D7688-3FC1-48D4-8F4E-5C379DF7E990",
    "isStale" : false,
    "radiusSD" : 5.88107607810571,
    "lastVisitDate" : "2024-04-27T03:00:47Z",
    "latitude" : -26.481650683478065
  },
  {
    "name" : "Clem Jones Promenade",
    "mapboxMakiIcon" : "picnic-site",
    "visitDays" : 1,
    "countryCode" : "au",
    "isStale" : false,
    "rtreeId" : 2115,
    "lastSaved" : "2025-12-26T20:44:46Z",
    "locality" : "South Brisbane",
    "latitude" : -27.47737075965071,
    "secondsFromGMT" : 36000,
    "visitCount" : 1,
    "id" : "63986340-ABBD-4F81-94AF-A671F1C060B5",
    "streetAddress" : "153 Little Stanley St",
    "radiusMean" : 8,
    "mapboxCategory" : "park",
    "lastVisitDate" : "2024-05-25T07:42:34Z",
    "mapboxPlaceId" : "poi.438086669862",
    "radiusSD" : 1.5935364709046622,
    "source" : "LocoKit",
    "longitude" : 153.02298720288434
  },
  {
    "name" : "Victoria Park Parking",
    "visitDays" : 1,
    "countryCode" : "au",
    "isStale" : false,
    "rtreeId" : 2117,
    "lastSaved" : "2025-12-26T20:50:42Z",
    "locality" : "Spring Hill",
    "latitude" : -27.452723151919297,
    "secondsFromGMT" : 36000,
    "visitCount" : 2,
    "id" : "6E8C432C-FCFE-401D-9EAB-F5355B7C5032",
    "streetAddress" : "Victoria Park",
    "radiusMean" : 8,
    "lastVisitDate" : "2024-06-02T06:39:34Z",
    "radiusSD" : 1.5045695168555833,
    "source" : "LocoKit",
    "longitude" : 153.0271071377929
  },
  {
    "name" : "Tesla wall connectors",
    "visitDays" : 1,
    "isStale" : false,
    "rtreeId" : 2139,
    "lastSaved" : "2025-12-21T16:22:53Z",
    "latitude" : -28.848357292669426,
    "secondsFromGMT" : 36000,
    "visitCount" : 1,
    "id" : "61B8E26D-6550-496F-A028-8CF6644C33F2",
    "streetAddress" : "49 Wren La",
    "radiusMean" : 8,
    "lastVisitDate" : "2024-07-10T00:19:09Z",
    "radiusSD" : 1.675845310168527,
    "source" : "LocoKit",
    "longitude" : 151.92028602969
  },
  {
    "name" : "Tesla Service Centre",
    "visitDays" : 1,
    "isStale" : false,
    "rtreeId" : 2146,
    "lastSaved" : "2025-12-21T16:22:54Z",
    "latitude" : -27.436295257202357,
    "secondsFromGMT" : 36000,
    "visitCount" : 3,
    "id" : "6D6E1863-A3F3-4906-A73F-5A130B036BFE",
    "streetAddress" : "594 Curtin Av E",
    "radiusMean" : 8,
    "lastVisitDate" : "2024-07-12T04:04:53Z",
    "radiusSD" : 5.295066674900399,
    "source" : "LocoKit",
    "longitude" : 153.10100565005683
  },
  {
    "name" : "Shell",
    "mapboxMakiIcon" : "fuel",
    "visitDays" : 1,
    "isStale" : false,
    "rtreeId" : 2148,
    "lastSaved" : "2025-12-21T16:22:54Z",
    "latitude" : -27.983792869956144,
    "secondsFromGMT" : 36000,
    "visitCount" : 1,
    "id" : "6C8250D5-1708-4591-BDDE-1EE18D0F1474",
    "streetAddress" : "6776 Cunningham Hwy.",
    "radiusMean" : 8,
    "mapboxCategory" : "gas station, fuel, gas",
    "lastVisitDate" : "2024-07-11T07:04:35Z",
    "mapboxPlaceId" : "poi.867583428727",
    "radiusSD" : 0.10452981376200811,
    "source" : "LocoKit",
    "longitude" : 152.54559924350838
  },
  {
    "name" : "Evie Chargers",
    "visitDays" : 1,
    "countryCode" : "au",
    "isStale" : false,
    "rtreeId" : 2153,
    "lastSaved" : "2025-12-24T05:19:23Z",
    "locality" : "Windsor",
    "latitude" : -27.437200191662694,
    "secondsFromGMT" : 36000,
    "visitCount" : 2,
    "id" : "680EB3A1-A1DC-4CE6-AB4B-5473E47E2117",
    "streetAddress" : "Homezone Windsor",
    "radiusMean" : 8,
    "lastVisitDate" : "2024-07-31T00:42:06Z",
    "radiusSD" : 1.2948184317467455,
    "source" : "LocoKit",
    "longitude" : 153.0237021974768
  },
  {
    "name" : "Buderim Ginger Factory",
    "visitDays" : 4,
    "countryCode" : "au",
    "isStale" : false,
    "rtreeId" : 2157,
    "lastSaved" : "2026-01-02T14:04:09Z",
    "locality" : "Yandina",
    "latitude" : -26.55423685744631,
    "secondsFromGMT" : 36000,
    "visitCount" : 9,
    "id" : "688F7430-B8BF-4935-AE5E-9C29A779BF0F",
    "streetAddress" : "Yandina",
    "radiusMean" : 25.148563106922936,
    "mapboxCategory" : "food and drink, shop",
    "lastVisitDate" : "2026-01-02T03:25:01Z",
    "mapboxPlaceId" : "poi.618475313859",
    "radiusSD" : 14.847311020132,
    "source" : "LocoKit",
    "longitude" : 152.95980073130224
  },
  {
    "name" : "Buranda Village Shopping Centre",
    "visitDays" : 1,
    "countryCode" : "au",
    "isStale" : false,
    "rtreeId" : 2208,
    "lastSaved" : "2025-12-26T20:47:08Z",
    "locality" : "Woolloongabba",
    "latitude" : -27.500761075709523,
    "secondsFromGMT" : 36000,
    "visitCount" : 1,
    "id" : "6792FDC8-3AD1-4813-A7FE-C30B38FB120B",
    "streetAddress" : "Buranda Village",
    "radiusMean" : 8,
    "lastVisitDate" : "2024-11-21T09:17:59Z",
    "radiusSD" : 0,
    "source" : "LocoKit",
    "longitude" : 153.03579945524737
  },
  {
    "name" : "Mater Health And Wellness",
    "visitDays" : 1,
    "countryCode" : "au",
    "isStale" : false,
    "rtreeId" : 2224,
    "lastSaved" : "2025-12-26T20:44:52Z",
    "locality" : "South Brisbane",
    "latitude" : -27.485869629641247,
    "secondsFromGMT" : 36000,
    "visitCount" : 1,
    "id" : "6FAD7746-9796-4D5F-8A71-9D01E2F5E88F",
    "streetAddress" : "Mater Children's Private Brisbane",
    "radiusMean" : 11.177135852432928,
    "lastVisitDate" : "2025-01-15T04:04:06Z",
    "radiusSD" : 8.543997374560208,
    "source" : "LocoKit",
    "longitude" : 153.02715413920205
  },
  {
    "lastSaved" : "2025-12-21T16:23:05Z",
    "streetAddress" : "3390 Pacific Hwy",
    "id" : "69970A06-22A5-4B6D-ACE2-6EEF0253D051",
    "visitDays" : 1,
    "name" : "BP pulse",
    "longitude" : 153.12831021966326,
    "latitude" : -27.622171429268896,
    "source" : "LocoKit",
    "isStale" : false,
    "radiusMean" : 8,
    "visitCount" : 1,
    "rtreeId" : 2245,
    "radiusSD" : 4.830792833447737,
    "secondsFromGMT" : 36000,
    "lastVisitDate" : "2025-03-24T10:52:23Z"
  },
  {
    "lastSaved" : "2026-01-01T22:46:25Z",
    "locality" : "Mount Gravatt",
    "streetAddress" : "1593 Logan Rd",
    "id" : "60ECCE18-8F60-4DC5-AEDE-D712AFA439A5",
    "visitDays" : 14,
    "name" : "Mt Gravatt Scout Den",
    "longitude" : 153.08088330787103,
    "latitude" : -27.545515101029107,
    "countryCode" : "au",
    "source" : "LocoKit",
    "isStale" : false,
    "radiusMean" : 15.461454747064911,
    "visitCount" : 26,
    "rtreeId" : 2253,
    "radiusSD" : 15.871867979870796,
    "secondsFromGMT" : 36000,
    "lastVisitDate" : "2025-12-31T22:20:00Z"
  },
  {
    "lastSaved" : "2025-12-21T16:23:06Z",
    "streetAddress" : "Arndale Shopping Centre",
    "id" : "617A1B10-9C78-4C9D-BD2C-1CE54D0D31AD",
    "visitDays" : 1,
    "name" : "Evie EV Charger, Springwood",
    "longitude" : 153.1251069349162,
    "latitude" : -27.6129598048557,
    "source" : "LocoKit",
    "isStale" : false,
    "radiusMean" : 8,
    "visitCount" : 1,
    "rtreeId" : 2256,
    "radiusSD" : 0.9120375585434661,
    "secondsFromGMT" : 36000,
    "lastVisitDate" : "2025-04-22T08:40:43Z"
  },
  {
    "lastSaved" : "2025-12-21T16:23:06Z",
    "streetAddress" : "100A Granard Rd",
    "id" : "6738DE12-63BD-4454-BEFC-0A145DFF6A42",
    "visitDays" : 1,
    "name" : "Coles Express",
    "longitude" : 153.01585400818834,
    "latitude" : -27.55820298987847,
    "source" : "LocoKit",
    "isStale" : false,
    "radiusMean" : 8,
    "visitCount" : 1,
    "rtreeId" : 2257,
    "radiusSD" : 4.744679970976532,
    "secondsFromGMT" : 36000,
    "lastVisitDate" : "2025-04-24T03:00:03Z"
  },
  {
    "lastSaved" : "2025-12-21T16:23:10Z",
    "streetAddress" : "Towncentre News",
    "id" : "6EE5C7CF-3FEE-4111-B990-C81E9F32B06F",
    "visitDays" : 1,
    "name" : "Evie EV Charger",
    "longitude" : 153.28371424575454,
    "latitude" : -27.586792516125506,
    "source" : "LocoKit",
    "isStale" : false,
    "radiusMean" : 8,
    "visitCount" : 1,
    "rtreeId" : 2290,
    "radiusSD" : 2.9803172276046928,
    "secondsFromGMT" : 36000,
    "lastVisitDate" : "2025-06-19T12:59:07Z"
  },
  {
    "lastSaved" : "2025-12-21T16:23:10Z",
    "streetAddress" : "3509 Pacific Hwy",
    "id" : "64B31F73-0D7F-498D-B7E5-0898AFC595A1",
    "visitDays" : 1,
    "name" : "BYD, Springwood",
    "longitude" : 153.13266143092886,
    "latitude" : -27.63499756693532,
    "source" : "LocoKit",
    "isStale" : false,
    "radiusMean" : 9.286514098734042,
    "visitCount" : 2,
    "rtreeId" : 2291,
    "radiusSD" : 5.346727186029668,
    "secondsFromGMT" : 36000,
    "lastVisitDate" : "2025-06-19T06:43:26Z"
  },
  {
    "lastSaved" : "2025-12-21T16:23:10Z",
    "streetAddress" : "Venman Bushland National Park",
    "id" : "6EF68B53-68D1-4AA4-8900-E54C4B46BFF9",
    "visitDays" : 4,
    "name" : "Venman Bushland Picnic Area",
    "longitude" : 153.2045256256039,
    "latitude" : -27.631734104672056,
    "source" : "LocoKit",
    "isStale" : false,
    "radiusMean" : 11.655200900435474,
    "visitCount" : 8,
    "rtreeId" : 2295,
    "radiusSD" : 19.815471346394705,
    "secondsFromGMT" : 36000,
    "lastVisitDate" : "2025-10-19T00:46:12Z"
  },
  {
    "lastSaved" : "2025-12-21T16:23:11Z",
    "streetAddress" : "Mount Matherson Trail",
    "id" : "62DA3238-8342-4564-83E7-4D4B406D883C",
    "visitDays" : 1,
    "name" : "Spicers Gap Picnic area",
    "longitude" : 152.42568650903485,
    "latitude" : -28.072725892167252,
    "source" : "LocoKit",
    "isStale" : false,
    "radiusMean" : 10.106115426103681,
    "visitCount" : 2,
    "rtreeId" : 2300,
    "radiusSD" : 4.048549921319336,
    "secondsFromGMT" : 36000,
    "lastVisitDate" : "2025-08-16T03:58:29Z"
  },
  {
    "lastSaved" : "2025-12-21T16:23:14Z",
    "streetAddress" : "Crows Nest",
    "id" : "6C32FCE0-0A90-487A-9A5F-373AEAD31202",
    "visitDays" : 1,
    "name" : "Lake Perseverance Lookout",
    "longitude" : 152.1182352434474,
    "latitude" : -27.2882610970324,
    "source" : "LocoKit",
    "isStale" : false,
    "radiusMean" : 8,
    "visitCount" : 1,
    "rtreeId" : 2321,
    "radiusSD" : 2.1677206684385446,
    "secondsFromGMT" : 36000,
    "lastVisitDate" : "2025-10-04T03:12:53Z"
  },
  {
    "lastSaved" : "2025-12-21T16:23:14Z",
    "streetAddress" : "Southeast Inner Brisbane",
    "id" : "6B17AC72-ED54-4FCA-9910-924624482737",
    "visitDays" : 1,
    "name" : "Whites Hill Reserve Carpark ",
    "longitude" : 153.07974739280675,
    "latitude" : -27.50887829969568,
    "source" : "LocoKit",
    "isStale" : false,
    "radiusMean" : 8,
    "visitCount" : 1,
    "rtreeId" : 2329,
    "radiusSD" : 2.407141785805281,
    "secondsFromGMT" : 36000,
    "lastVisitDate" : "2025-10-31T21:07:19Z"
  },
  {
    "isStale" : false,
    "rtreeId" : 2348,
    "longitude" : 144.96438882651302,
    "lastVisitDate" : "2025-11-13T03:56:02Z",
    "latitude" : -37.81721324272231,
    "lastSaved" : "2025-12-21T16:23:17Z",
    "id" : "6354EECA-94FC-4AF3-B704-B7A6ECF9877E",
    "radiusMean" : 8,
    "streetAddress" : "290–292 Flinders La",
    "name" : "Crown Watches",
    "radiusSD" : 2.017618264908497,
    "secondsFromGMT" : 39600,
    "source" : "LocoKit",
    "visitCount" : 1,
    "visitDays" : 1
  },
  {
    "isStale" : false,
    "rtreeId" : 2349,
    "longitude" : 144.96574948972147,
    "lastVisitDate" : "2025-11-13T04:17:10Z",
    "latitude" : -37.815580765356266,
    "lastSaved" : "2025-12-21T16:23:17Z",
    "id" : "66D9EE70-5332-43E5-AD2A-1D9201DECF5D",
    "radiusMean" : 8,
    "streetAddress" : "234 Collins St",
    "name" : "Anime Store",
    "radiusSD" : 2.267698739575698,
    "secondsFromGMT" : 39600,
    "source" : "LocoKit",
    "visitCount" : 1,
    "visitDays" : 1
  },
  {
    "isStale" : false,
    "rtreeId" : 2353,
    "longitude" : 144.91371246593968,
    "lastVisitDate" : "2025-11-14T23:05:11Z",
    "latitude" : -37.780454088019184,
    "lastSaved" : "2025-12-21T16:23:17Z",
    "id" : "65B52743-D586-4FB6-A675-7EE187C06DFA",
    "radiusMean" : 44.38511566699809,
    "streetAddress" : "Melbourne Showgrounds",
    "name" : "Melbourne Showgrounds",
    "radiusSD" : 24.191664993679357,
    "secondsFromGMT" : 39600,
    "source" : "LocoKit",
    "visitCount" : 12,
    "visitDays" : 2
  },
  {
    "isStale" : false,
    "rtreeId" : 2358,
    "longitude" : 144.97341994916698,
    "lastVisitDate" : "2025-11-15T23:06:40Z",
    "latitude" : -37.830386980136396,
    "lastSaved" : "2025-12-21T16:23:18Z",
    "id" : "64B4323C-0CCC-49A2-8FB5-B4183BC97194",
    "radiusMean" : 19.277476622806162,
    "streetAddress" : "Shrine of Remembrance",
    "name" : "Shrine of Rememberance",
    "radiusSD" : 10.114851755633943,
    "secondsFromGMT" : 39600,
    "source" : "LocoKit",
    "visitCount" : 2,
    "visitDays" : 1
  },
  {
    "isStale" : false,
    "rtreeId" : 2374,
    "googlePlaceId" : "ChIJ95FR4a9bkWsRKIO9GqQczGU",
    "longitude" : 153.19171412080593,
    "lastVisitDate" : "2025-12-15T04:11:55Z",
    "latitude" : -27.68117282386308,
    "lastSaved" : "2025-12-21T16:23:20Z",
    "id" : "688270C1-6C62-44B1-9898-ADDEA2D06941",
    "googlePrimaryType" : "store",
    "radiusMean" : 10.65805207184439,
    "streetAddress" : "1\/9 Babdoyle Street, Loganholme",
    "name" : "Savage Tech Australia",
    "radiusSD" : 4.879562981446308,
    "secondsFromGMT" : 36000,
    "source" : "LocoKit",
    "visitCount" : 1,
    "visitDays" : 1
  },
  {
    "isStale" : false,
    "rtreeId" : 2375,
    "googlePlaceId" : "ChIJA28SF8dakWsRkiDeOlrm-UM",
    "longitude" : 153.04047621957181,
    "lastVisitDate" : "2025-12-05T21:50:23Z",
    "latitude" : -27.53913584831013,
    "lastSaved" : "2025-12-21T16:23:20Z",
    "id" : "67B27378-65EF-48D4-B525-7E9A75D9ED02",
    "locality" : "Nathan",
    "radiusMean" : 8,
    "streetAddress" : "Toohey Forest Park",
    "countryCode" : "au",
    "radiusSD" : 0.5877115019455296,
    "secondsFromGMT" : 36000,
    "name" : "Lophostemon Track",
    "source" : "LocoKit",
    "googlePrimaryType" : "route",
    "visitCount" : 1,
    "visitDays" : 1
  }
]